{
    "playlist_info": {
        "name": "Bingstream Auto Update Playlist",
        "telegram": "https://t.me/livesportsplay",
        "owner": "Md Sohanur Rahman Hady",
        "last_update_time": "4:46:34 AM 29-03-2026"
    },
    "channels": [
        {
            "Category": "LIVE EVENT",
            "League": "Intro",
            "Team 1 Name": "Bingstream",
            "Team 2 Name": "Intro",
            "Team 1 Logo": "https://github.com/srhady/Hady/raw/refs/heads/main/1773124095740.png",
            "Team 2 Logo": "https://github.com/srhady/Hady/raw/refs/heads/main/1773124095740.png",
            "Match Title": "Intro",
            "Match Poster": "https://github.com/srhady/Hady/raw/refs/heads/main/1773124095740.png",
            "Match Status": "Live",
            "Start Time": "Always",
            "User-Agent": "Mozilla/5.0 (Linux; Android 10; K) AppleWebKit/537.36 (KHTML, like Gecko) Chrome/120.0.0.0 Mobile Safari/537.36",
            "Referer": "https://api2.ifnewgen.xyz/",
            "Stream URL": "https://github.com/srhady/Hady/raw/refs/heads/main/video_20260310_131739_edit.mp4"
        },
        {
            "Category": "MMA",
            "League": "UFC FIGHT NIGHT",
            "Team 1 Name": "",
            "Team 2 Name": "",
            "Team 1 Logo": "",
            "Team 2 Logo": "",
            "Match Title": "PRELIMS | UFC FIGHT NIGHT",
            "Match Poster": "https://placehold.co/800x450/ffffff/000000.png?text=PRELIMS%0AUFC%20FIGHT%20NIGHT&font=Oswald",
            "Match Status": "Live",
            "Start Time": "Live Now",
            "User-Agent": "Mozilla/5.0 (Linux; Android 10; K) AppleWebKit/537.36 (KHTML, like Gecko) Chrome/120.0.0.0 Mobile Safari/537.36",
            "Referer": "https://api2.ifnewgen.xyz/",
            "Stream URL": "https://livecdn-bp-livestream.linewgen.xyz/stream/5/chunks.m3u8?is_vip=false&token=f6cd7658616c7e8f7f0caf7c97ca9584948d6adf&x-sign=83b03c75b5921a3f043facc264072edb&x-time=1774731720"
        },
        {
            "Category": "Friendlies",
            "League": "Friendlies",
            "Team 1 Name": "England",
            "Team 2 Name": "Japan",
            "Team 1 Logo": "https://static-live.linewgen.xyz/live/bing/img/rapid/teams/10.png",
            "Team 2 Logo": "https://static-live.linewgen.xyz/live/bing/img/rapid/teams/12.png",
            "Match Title": "England VS Japan | Friendlies",
            "Match Poster": "https://placehold.co/800x450/ffffff/000000.png?text=England%0AVS%0AJapan%0AFriendlies&font=Oswald",
            "Match Status": "Upcoming",
            "Start Time": "12:45 AM 01-04-2026",
            "User-Agent": "Mozilla/5.0 (Linux; Android 10; K) AppleWebKit/537.36 (KHTML, like Gecko) Chrome/120.0.0.0 Mobile Safari/537.36",
            "Referer": "https://api2.ifnewgen.xyz/",
            "Stream URL": ""
        },
        {
            "Category": "Friendlies",
            "League": "Friendlies",
            "Team 1 Name": "Netherlands",
            "Team 2 Name": "Ecuador",
            "Team 1 Logo": "https://static-live.linewgen.xyz/live/bing/img/rapid/teams/1118.png",
            "Team 2 Logo": "https://static-live.linewgen.xyz/live/bing/img/rapid/teams/2382.png",
            "Match Title": "Netherlands VS Ecuador | Friendlies",
            "Match Poster": "https://placehold.co/800x450/ffffff/000000.png?text=Netherlands%0AVS%0AEcuador%0AFriendlies&font=Oswald",
            "Match Status": "Upcoming",
            "Start Time": "12:45 AM 01-04-2026",
            "User-Agent": "Mozilla/5.0 (Linux; Android 10; K) AppleWebKit/537.36 (KHTML, like Gecko) Chrome/120.0.0.0 Mobile Safari/537.36",
            "Referer": "https://api2.ifnewgen.xyz/",
            "Stream URL": ""
        },
        {
            "Category": "Friendlies",
            "League": "Friendlies",
            "Team 1 Name": "USA",
            "Team 2 Name": "Portugal",
            "Team 1 Logo": "https://static-live.linewgen.xyz/live/bing/img/rapid/teams/2384.png",
            "Team 2 Logo": "https://static-live.linewgen.xyz/live/bing/img/rapid/teams/27.png",
            "Match Title": "USA VS Portugal | Friendlies",
            "Match Poster": "https://placehold.co/800x450/ffffff/000000.png?text=USA%0AVS%0APortugal%0AFriendlies&font=Oswald",
            "Match Status": "Upcoming",
            "Start Time": "5:00 AM 01-04-2026",
            "User-Agent": "Mozilla/5.0 (Linux; Android 10; K) AppleWebKit/537.36 (KHTML, like Gecko) Chrome/120.0.0.0 Mobile Safari/537.36",
            "Referer": "https://api2.ifnewgen.xyz/",
            "Stream URL": ""
        },
        {
            "Category": "Friendlies",
            "League": "Friendlies",
            "Team 1 Name": "Brazil",
            "Team 2 Name": "Croatia",
            "Team 1 Logo": "https://static-live.linewgen.xyz/live/bing/img/rapid/teams/6.png",
            "Team 2 Logo": "https://static-live.linewgen.xyz/live/bing/img/rapid/teams/3.png",
            "Match Title": "Brazil VS Croatia | Friendlies",
            "Match Poster": "https://placehold.co/800x450/ffffff/000000.png?text=Brazil%0AVS%0ACroatia%0AFriendlies&font=Oswald",
            "Match Status": "Upcoming",
            "Start Time": "6:00 AM 01-04-2026",
            "User-Agent": "Mozilla/5.0 (Linux; Android 10; K) AppleWebKit/537.36 (KHTML, like Gecko) Chrome/120.0.0.0 Mobile Safari/537.36",
            "Referer": "https://api2.ifnewgen.xyz/",
            "Stream URL": ""
        },
        {
            "Category": "Championship",
            "League": "Championship",
            "Team 1 Name": "Leicester",
            "Team 2 Name": "Preston",
            "Team 1 Logo": "https://static-live.linewgen.xyz/live/bing/img/rapid/teams/46.png",
            "Team 2 Logo": "https://static-live.linewgen.xyz/live/bing/img/rapid/teams/59.png",
            "Match Title": "Leicester VS Preston | Championship",
            "Match Poster": "https://placehold.co/800x450/ffffff/000000.png?text=Leicester%0AVS%0APreston%0AChampionship&font=Oswald",
            "Match Status": "Upcoming",
            "Start Time": "8:00 PM 03-04-2026",
            "User-Agent": "Mozilla/5.0 (Linux; Android 10; K) AppleWebKit/537.36 (KHTML, like Gecko) Chrome/120.0.0.0 Mobile Safari/537.36",
            "Referer": "https://api2.ifnewgen.xyz/",
            "Stream URL": ""
        },
        {
            "Category": "Pro League",
            "League": "Pro League",
            "Team 1 Name": "Al-Nassr",
            "Team 2 Name": "Al Najma",
            "Team 1 Logo": "https://static-live.linewgen.xyz/live/bing/img/rapid/teams/2939.png",
            "Team 2 Logo": "https://static-live.linewgen.xyz/live/bing/img/rapid/teams/2992.png",
            "Match Title": "Al-Nassr VS Al Najma | Pro League",
            "Match Poster": "https://placehold.co/800x450/ffffff/000000.png?text=Al-Nassr%0AVS%0AAl%20Najma%0APro%20League&font=Oswald",
            "Match Status": "Upcoming",
            "Start Time": "12:00 AM 04-04-2026",
            "User-Agent": "Mozilla/5.0 (Linux; Android 10; K) AppleWebKit/537.36 (KHTML, like Gecko) Chrome/120.0.0.0 Mobile Safari/537.36",
            "Referer": "https://api2.ifnewgen.xyz/",
            "Stream URL": ""
        },
        {
            "Category": "Ligue 1",
            "League": "Ligue 1",
            "Team 1 Name": "Paris Saint Germain",
            "Team 2 Name": "Toulouse",
            "Team 1 Logo": "https://static-live.linewgen.xyz/live/bing/img/rapid/teams/85.png",
            "Team 2 Logo": "https://static-live.linewgen.xyz/live/bing/img/rapid/teams/96.png",
            "Match Title": "Paris Saint Germain VS Toulouse | Ligue 1",
            "Match Poster": "https://placehold.co/800x450/ffffff/000000.png?text=Paris%20Saint%20Germain%0AVS%0AToulouse%0ALigue%201&font=Oswald",
            "Match Status": "Upcoming",
            "Start Time": "12:45 AM 04-04-2026",
            "User-Agent": "Mozilla/5.0 (Linux; Android 10; K) AppleWebKit/537.36 (KHTML, like Gecko) Chrome/120.0.0.0 Mobile Safari/537.36",
            "Referer": "https://api2.ifnewgen.xyz/",
            "Stream URL": ""
        },
        {
            "Category": "Football",
            "League": "Friendlies",
            "Team 1 Name": "Mexico",
            "Team 2 Name": "Portugal",
            "Team 1 Logo": "https://static-live.linewgen.xyz/live/bing/img/rapid/teams/16.png",
            "Team 2 Logo": "https://static-live.linewgen.xyz/live/bing/img/rapid/teams/27.png",
            "Match Title": "Mexico VS Portugal | Friendlies",
            "Match Poster": "https://placehold.co/800x450/ffffff/000000.png?text=Mexico%0AVS%0APortugal%0AFriendlies&font=Oswald",
            "Match Status": "Upcoming",
            "Start Time": "7:00 AM 29-03-2026",
            "User-Agent": "Mozilla/5.0 (Linux; Android 10; K) AppleWebKit/537.36 (KHTML, like Gecko) Chrome/120.0.0.0 Mobile Safari/537.36",
            "Referer": "https://api2.ifnewgen.xyz/",
            "Stream URL": ""
        },
        {
            "Category": "Football",
            "League": "A-League Women",
            "Team 1 Name": "Wellington Phoenix W",
            "Team 2 Name": "Western Sydney Wanderers W",
            "Team 1 Logo": "https://static-live.linewgen.xyz/live/bing/img/rapid/teams/17905.png",
            "Team 2 Logo": "https://static-live.linewgen.xyz/live/bing/img/rapid/teams/1974.png",
            "Match Title": "Wellington Phoenix W VS Western Sydney Wanderers W | A-League Women",
            "Match Poster": "https://placehold.co/800x450/ffffff/000000.png?text=Wellington%20Phoenix%20W%0AVS%0AWestern%20Sydney%20Wanderers%20W%0AA-League%20Women&font=Oswald",
            "Match Status": "Upcoming",
            "Start Time": "9:00 AM 29-03-2026",
            "User-Agent": "Mozilla/5.0 (Linux; Android 10; K) AppleWebKit/537.36 (KHTML, like Gecko) Chrome/120.0.0.0 Mobile Safari/537.36",
            "Referer": "https://api2.ifnewgen.xyz/",
            "Stream URL": ""
        },
        {
            "Category": "Football",
            "League": "AFL Premiership",
            "Team 1 Name": "",
            "Team 2 Name": "",
            "Team 1 Logo": "",
            "Team 2 Logo": "",
            "Match Title": "Melbourne VS Carlton | AFL Premiership",
            "Match Poster": "https://placehold.co/800x450/ffffff/000000.png?text=Melbourne%0AVS%0ACarlton%0AAFL%20Premiership&font=Oswald",
            "Match Status": "Upcoming",
            "Start Time": "10:00 AM 29-03-2026",
            "User-Agent": "Mozilla/5.0 (Linux; Android 10; K) AppleWebKit/537.36 (KHTML, like Gecko) Chrome/120.0.0.0 Mobile Safari/537.36",
            "Referer": "https://api2.ifnewgen.xyz/",
            "Stream URL": ""
        },
        {
            "Category": "Football",
            "League": "AFC Women's Champions League",
            "Team 1 Name": "Melbourne City",
            "Team 2 Name": "Nasaf",
            "Team 1 Logo": "https://static-live.linewgen.xyz/live/bing/img/soccer/teams/27/315.png",
            "Team 2 Logo": "https://static-live.linewgen.xyz/live/bing/img/rapid/teams/4215.png",
            "Match Title": "Melbourne City VS Nasaf | AFC Women's Champions League",
            "Match Poster": "https://placehold.co/800x450/ffffff/000000.png?text=Melbourne%20City%0AVS%0ANasaf%0AAFC%20Women's%20Champions%20League&font=Oswald",
            "Match Status": "Upcoming",
            "Start Time": "10:00 AM 29-03-2026",
            "User-Agent": "Mozilla/5.0 (Linux; Android 10; K) AppleWebKit/537.36 (KHTML, like Gecko) Chrome/120.0.0.0 Mobile Safari/537.36",
            "Referer": "https://api2.ifnewgen.xyz/",
            "Stream URL": ""
        },
        {
            "Category": "Football",
            "League": "A-League Women",
            "Team 1 Name": "Central Coast Mariners W",
            "Team 2 Name": "Canberra United W",
            "Team 1 Logo": "https://static-live.linewgen.xyz/live/bing/img/rapid/teams/22292.png",
            "Team 2 Logo": "https://static-live.linewgen.xyz/live/bing/img/rapid/teams/1970.png",
            "Match Title": "Central Coast Mariners W VS Canberra United W | A-League Women",
            "Match Poster": "https://placehold.co/800x450/ffffff/000000.png?text=Central%20Coast%20Mariners%20W%0AVS%0ACanberra%20United%20W%0AA-League%20Women&font=Oswald",
            "Match Status": "Upcoming",
            "Start Time": "11:00 AM 29-03-2026",
            "User-Agent": "Mozilla/5.0 (Linux; Android 10; K) AppleWebKit/537.36 (KHTML, like Gecko) Chrome/120.0.0.0 Mobile Safari/537.36",
            "Referer": "https://api2.ifnewgen.xyz/",
            "Stream URL": ""
        },
        {
            "Category": "Football",
            "League": "AFC Women's Champions League",
            "Team 1 Name": "Wuhan Jiangda W",
            "Team 2 Name": "Suwon City FC",
            "Team 1 Logo": "https://static-live.linewgen.xyz/live/bing/img/rapid/teams/24895.png",
            "Team 2 Logo": "https://static-live.linewgen.xyz/live/bing/img/rapid/teams/2756.png",
            "Match Title": "Wuhan Jiangda W VS Suwon City FC | AFC Women's Champions League",
            "Match Poster": "https://placehold.co/800x450/ffffff/000000.png?text=Wuhan%20Jiangda%20W%0AVS%0ASuwon%20City%20FC%0AAFC%20Women's%20Champions%20League&font=Oswald",
            "Match Status": "Upcoming",
            "Start Time": "5:00 PM 29-03-2026",
            "User-Agent": "Mozilla/5.0 (Linux; Android 10; K) AppleWebKit/537.36 (KHTML, like Gecko) Chrome/120.0.0.0 Mobile Safari/537.36",
            "Referer": "https://api2.ifnewgen.xyz/",
            "Stream URL": ""
        },
        {
            "Category": "Football",
            "League": "FA WSL",
            "Team 1 Name": "Chelsea W",
            "Team 2 Name": "Aston Villa W",
            "Team 1 Logo": "https://static-live.linewgen.xyz/live/bing/img/rapid/teams/1853.png",
            "Team 2 Logo": "https://static-live.linewgen.xyz/live/bing/img/rapid/teams/14219.png",
            "Match Title": "Chelsea W VS Aston Villa W | FA WSL",
            "Match Poster": "https://placehold.co/800x450/ffffff/000000.png?text=Chelsea%20W%0AVS%0AAston%20Villa%20W%0AFA%20WSL&font=Oswald",
            "Match Status": "Upcoming",
            "Start Time": "5:00 PM 29-03-2026",
            "User-Agent": "Mozilla/5.0 (Linux; Android 10; K) AppleWebKit/537.36 (KHTML, like Gecko) Chrome/120.0.0.0 Mobile Safari/537.36",
            "Referer": "https://api2.ifnewgen.xyz/",
            "Stream URL": ""
        },
        {
            "Category": "Football",
            "League": "FA WSL",
            "Team 1 Name": "West Ham W",
            "Team 2 Name": "London City Lionesses",
            "Team 1 Logo": "https://static-live.linewgen.xyz/live/bing/img/rapid/teams/1856.png",
            "Team 2 Logo": "https://static-live.linewgen.xyz/live/bing/img/rapid/teams/15406.png",
            "Match Title": "West Ham W VS London City Lionesses | FA WSL",
            "Match Poster": "https://placehold.co/800x450/ffffff/000000.png?text=West%20Ham%20W%0AVS%0ALondon%20City%20Lionesses%0AFA%20WSL&font=Oswald",
            "Match Status": "Upcoming",
            "Start Time": "5:00 PM 29-03-2026",
            "User-Agent": "Mozilla/5.0 (Linux; Android 10; K) AppleWebKit/537.36 (KHTML, like Gecko) Chrome/120.0.0.0 Mobile Safari/537.36",
            "Referer": "https://api2.ifnewgen.xyz/",
            "Stream URL": ""
        },
        {
            "Category": "Football",
            "League": "Segunda División",
            "Team 1 Name": "Eibar",
            "Team 2 Name": "Las Palmas",
            "Team 1 Logo": "https://static-live.linewgen.xyz/live/bing/img/rapid/teams/545.png",
            "Team 2 Logo": "https://static-live.linewgen.xyz/live/bing/img/rapid/teams/534.png",
            "Match Title": "Eibar VS Las Palmas | Segunda División",
            "Match Poster": "https://placehold.co/800x450/ffffff/000000.png?text=Eibar%0AVS%0ALas%20Palmas%0ASegunda%20Divisi%C3%B3n&font=Oswald",
            "Match Status": "Upcoming",
            "Start Time": "6:00 PM 29-03-2026",
            "User-Agent": "Mozilla/5.0 (Linux; Android 10; K) AppleWebKit/537.36 (KHTML, like Gecko) Chrome/120.0.0.0 Mobile Safari/537.36",
            "Referer": "https://api2.ifnewgen.xyz/",
            "Stream URL": ""
        },
        {
            "Category": "Football",
            "League": "Africa Cup of Nations - Qualification",
            "Team 1 Name": "South Sudan",
            "Team 2 Name": "Djibouti",
            "Team 1 Logo": "https://static-live.linewgen.xyz/live/bing/img/rapid/teams/1496.png",
            "Team 2 Logo": "https://static-live.linewgen.xyz/live/bing/img/rapid/teams/1535.png",
            "Match Title": "South Sudan VS Djibouti | Africa Cup of Nations - Qualification",
            "Match Poster": "https://placehold.co/800x450/ffffff/000000.png?text=South%20Sudan%0AVS%0ADjibouti%0AAfrica%20Cup%20of%20Nations%20-%20Qualification&font=Oswald",
            "Match Status": "Upcoming",
            "Start Time": "7:00 PM 29-03-2026",
            "User-Agent": "Mozilla/5.0 (Linux; Android 10; K) AppleWebKit/537.36 (KHTML, like Gecko) Chrome/120.0.0.0 Mobile Safari/537.36",
            "Referer": "https://api2.ifnewgen.xyz/",
            "Stream URL": ""
        },
        {
            "Category": "Football",
            "League": "Coppa Italia Women",
            "Team 1 Name": "Inter Milano W",
            "Team 2 Name": "Roma W",
            "Team 1 Logo": "https://static-live.linewgen.xyz/live/bing/img/rapid/teams/7533.png",
            "Team 2 Logo": "https://static-live.linewgen.xyz/live/bing/img/soccer/teams/1/230721.png",
            "Match Title": "Inter Milano W VS Roma W | Coppa Italia Women",
            "Match Poster": "https://placehold.co/800x450/ffffff/000000.png?text=Inter%20Milano%20W%0AVS%0ARoma%20W%0ACoppa%20Italia%20Women&font=Oswald",
            "Match Status": "Upcoming",
            "Start Time": "7:00 PM 29-03-2026",
            "User-Agent": "Mozilla/5.0 (Linux; Android 10; K) AppleWebKit/537.36 (KHTML, like Gecko) Chrome/120.0.0.0 Mobile Safari/537.36",
            "Referer": "https://api2.ifnewgen.xyz/",
            "Stream URL": ""
        },
        {
            "Category": "Football",
            "League": "Friendlies",
            "Team 1 Name": "Armenia",
            "Team 2 Name": "Belarus",
            "Team 1 Logo": "https://static-live.linewgen.xyz/live/bing/img/rapid/teams/1094.png",
            "Team 2 Logo": "https://static-live.linewgen.xyz/live/bing/img/rapid/teams/1100.png",
            "Match Title": "Armenia VS Belarus | Friendlies",
            "Match Poster": "https://placehold.co/800x450/ffffff/000000.png?text=Armenia%0AVS%0ABelarus%0AFriendlies&font=Oswald",
            "Match Status": "Upcoming",
            "Start Time": "7:00 PM 29-03-2026",
            "User-Agent": "Mozilla/5.0 (Linux; Android 10; K) AppleWebKit/537.36 (KHTML, like Gecko) Chrome/120.0.0.0 Mobile Safari/537.36",
            "Referer": "https://api2.ifnewgen.xyz/",
            "Stream URL": ""
        },
        {
            "Category": "Football",
            "League": "Friendlies",
            "Team 1 Name": "Lithuania",
            "Team 2 Name": "Georgia",
            "Team 1 Logo": "https://static-live.linewgen.xyz/live/bing/img/rapid/teams/1097.png",
            "Team 2 Logo": "https://static-live.linewgen.xyz/live/bing/img/rapid/teams/1104.png",
            "Match Title": "Lithuania VS Georgia | Friendlies",
            "Match Poster": "https://placehold.co/800x450/ffffff/000000.png?text=Lithuania%0AVS%0AGeorgia%0AFriendlies&font=Oswald",
            "Match Status": "Upcoming",
            "Start Time": "7:00 PM 29-03-2026",
            "User-Agent": "Mozilla/5.0 (Linux; Android 10; K) AppleWebKit/537.36 (KHTML, like Gecko) Chrome/120.0.0.0 Mobile Safari/537.36",
            "Referer": "https://api2.ifnewgen.xyz/",
            "Stream URL": ""
        },
        {
            "Category": "Football",
            "League": "Frauen Bundesliga",
            "Team 1 Name": "VfL Wolfsburg W",
            "Team 2 Name": "Union Berlin W",
            "Team 1 Logo": "https://static-live.linewgen.xyz/live/bing/img/rapid/teams/1863.png",
            "Team 2 Logo": "https://static-live.linewgen.xyz/live/bing/img/rapid/teams/24133.png",
            "Match Title": "VfL Wolfsburg W VS Union Berlin W | Frauen Bundesliga",
            "Match Poster": "https://placehold.co/800x450/ffffff/000000.png?text=VfL%20Wolfsburg%20W%0AVS%0AUnion%20Berlin%20W%0AFrauen%20Bundesliga&font=Oswald",
            "Match Status": "Upcoming",
            "Start Time": "8:00 PM 29-03-2026",
            "User-Agent": "Mozilla/5.0 (Linux; Android 10; K) AppleWebKit/537.36 (KHTML, like Gecko) Chrome/120.0.0.0 Mobile Safari/537.36",
            "Referer": "https://api2.ifnewgen.xyz/",
            "Stream URL": ""
        },
        {
            "Category": "Football",
            "League": "FA WSL",
            "Team 1 Name": "Leicester City WFC",
            "Team 2 Name": "Brighton W",
            "Team 1 Logo": "https://static-live.linewgen.xyz/live/bing/img/rapid/teams/15404.png",
            "Team 2 Logo": "https://static-live.linewgen.xyz/live/bing/img/rapid/teams/1857.png",
            "Match Title": "Leicester City WFC VS Brighton W | FA WSL",
            "Match Poster": "https://placehold.co/800x450/ffffff/000000.png?text=Leicester%20City%20WFC%0AVS%0ABrighton%20W%0AFA%20WSL&font=Oswald",
            "Match Status": "Upcoming",
            "Start Time": "8:00 PM 29-03-2026",
            "User-Agent": "Mozilla/5.0 (Linux; Android 10; K) AppleWebKit/537.36 (KHTML, like Gecko) Chrome/120.0.0.0 Mobile Safari/537.36",
            "Referer": "https://api2.ifnewgen.xyz/",
            "Stream URL": ""
        },
        {
            "Category": "Football",
            "League": "Africa Cup of Nations - Qualification",
            "Team 1 Name": "Lesotho",
            "Team 2 Name": "Seychelles",
            "Team 1 Logo": "https://static-live.linewgen.xyz/live/bing/img/rapid/teams/1518.png",
            "Team 2 Logo": "https://static-live.linewgen.xyz/live/bing/img/rapid/teams/1515.png",
            "Match Title": "Lesotho VS Seychelles | Africa Cup of Nations - Qualification",
            "Match Poster": "https://placehold.co/800x450/ffffff/000000.png?text=Lesotho%0AVS%0ASeychelles%0AAfrica%20Cup%20of%20Nations%20-%20Qualification&font=Oswald",
            "Match Status": "Upcoming",
            "Start Time": "9:00 PM 29-03-2026",
            "User-Agent": "Mozilla/5.0 (Linux; Android 10; K) AppleWebKit/537.36 (KHTML, like Gecko) Chrome/120.0.0.0 Mobile Safari/537.36",
            "Referer": "https://api2.ifnewgen.xyz/",
            "Stream URL": ""
        },
        {
            "Category": "Football",
            "League": "Coppa Italia Women",
            "Team 1 Name": "Juventus W",
            "Team 2 Name": "Fiorentina W",
            "Team 1 Logo": "https://static-live.linewgen.xyz/live/bing/img/soccer/teams/21/229269.png",
            "Team 2 Logo": "https://static-live.linewgen.xyz/live/bing/img/rapid/teams/1880.png",
            "Match Title": "Juventus W VS Fiorentina W | Coppa Italia Women",
            "Match Poster": "https://placehold.co/800x450/ffffff/000000.png?text=Juventus%20W%0AVS%0AFiorentina%20W%0ACoppa%20Italia%20Women&font=Oswald",
            "Match Status": "Upcoming",
            "Start Time": "10:00 PM 29-03-2026",
            "User-Agent": "Mozilla/5.0 (Linux; Android 10; K) AppleWebKit/537.36 (KHTML, like Gecko) Chrome/120.0.0.0 Mobile Safari/537.36",
            "Referer": "https://api2.ifnewgen.xyz/",
            "Stream URL": ""
        },
        {
            "Category": "Football",
            "League": "Segunda División",
            "Team 1 Name": "Zaragoza",
            "Team 2 Name": "Racing Santander",
            "Team 1 Logo": "https://static-live.linewgen.xyz/live/bing/img/rapid/teams/732.png",
            "Team 2 Logo": "https://static-live.linewgen.xyz/live/bing/img/rapid/teams/4665.png",
            "Match Title": "Zaragoza VS Racing Santander | Segunda División",
            "Match Poster": "https://placehold.co/800x450/ffffff/000000.png?text=Zaragoza%0AVS%0ARacing%20Santander%0ASegunda%20Divisi%C3%B3n&font=Oswald",
            "Match Status": "Upcoming",
            "Start Time": "10:30 PM 29-03-2026",
            "User-Agent": "Mozilla/5.0 (Linux; Android 10; K) AppleWebKit/537.36 (KHTML, like Gecko) Chrome/120.0.0.0 Mobile Safari/537.36",
            "Referer": "https://api2.ifnewgen.xyz/",
            "Stream URL": ""
        },
        {
            "Category": "Tennis",
            "League": "ATP Challenger",
            "Team 1 Name": "",
            "Team 2 Name": "",
            "Team 1 Logo": "",
            "Team 2 Logo": "",
            "Match Title": "Morelia Open: Day 6 | ATP Challenger",
            "Match Poster": "https://placehold.co/800x450/ffffff/000000.png?text=Morelia%20Open%3A%20Day%206%0AATP%20Challenger&font=Oswald",
            "Match Status": "Upcoming",
            "Start Time": "5:00 AM 29-03-2026",
            "User-Agent": "Mozilla/5.0 (Linux; Android 10; K) AppleWebKit/537.36 (KHTML, like Gecko) Chrome/120.0.0.0 Mobile Safari/537.36",
            "Referer": "https://api2.ifnewgen.xyz/",
            "Stream URL": ""
        },
        {
            "Category": "Tennis",
            "League": "Naples Open",
            "Team 1 Name": "",
            "Team 2 Name": "",
            "Team 1 Logo": "",
            "Team 2 Logo": "",
            "Match Title": "Day 7 | Naples Open",
            "Match Poster": "https://placehold.co/800x450/ffffff/000000.png?text=Day%207%0ANaples%20Open&font=Oswald",
            "Match Status": "Upcoming",
            "Start Time": "8:00 AM 29-03-2026",
            "User-Agent": "Mozilla/5.0 (Linux; Android 10; K) AppleWebKit/537.36 (KHTML, like Gecko) Chrome/120.0.0.0 Mobile Safari/537.36",
            "Referer": "https://api2.ifnewgen.xyz/",
            "Stream URL": ""
        },
        {
            "Category": "Tennis",
            "League": "ATP Challenger",
            "Team 1 Name": "",
            "Team 2 Name": "",
            "Team 1 Logo": "",
            "Team 2 Logo": "",
            "Match Title": "Naples-ATP Singles Final | ATP Challenger",
            "Match Poster": "https://placehold.co/800x450/ffffff/000000.png?text=Naples-ATP%20Singles%20Final%0AATP%20Challenger&font=Oswald",
            "Match Status": "Upcoming",
            "Start Time": "7:00 PM 29-03-2026",
            "User-Agent": "Mozilla/5.0 (Linux; Android 10; K) AppleWebKit/537.36 (KHTML, like Gecko) Chrome/120.0.0.0 Mobile Safari/537.36",
            "Referer": "https://api2.ifnewgen.xyz/",
            "Stream URL": ""
        },
        {
            "Category": "Basketball",
            "League": "SLB",
            "Team 1 Name": "Manchester Basketball",
            "Team 2 Name": "Leicester Riders",
            "Team 1 Logo": "https://static-live.linewgen.xyz/live/bing/img/teams/42ad5ac314ab1c29bb40b99569ba2986.png",
            "Team 2 Logo": "https://static-live.linewgen.xyz/live/bing/img/teams/66696b2ff01e855e29ea38bb6626ebfa.png",
            "Match Title": "Manchester Basketball VS Leicester Riders | SLB",
            "Match Poster": "https://placehold.co/800x450/ffffff/000000.png?text=Manchester%20Basketball%0AVS%0ALeicester%20Riders%0ASLB&font=Oswald",
            "Match Status": "Upcoming",
            "Start Time": "8:00 PM 29-03-2026",
            "User-Agent": "Mozilla/5.0 (Linux; Android 10; K) AppleWebKit/537.36 (KHTML, like Gecko) Chrome/120.0.0.0 Mobile Safari/537.36",
            "Referer": "https://api2.ifnewgen.xyz/",
            "Stream URL": ""
        },
        {
            "Category": "Basketball",
            "League": "SLB",
            "Team 1 Name": "Sheffield Sharks",
            "Team 2 Name": "Surrey 89ers",
            "Team 1 Logo": "https://static-live.linewgen.xyz/live/bing/img/teams/9368af4682ffba87b499887792f1caf0.png",
            "Team 2 Logo": "https://static-live.linewgen.xyz/live/bing/img/teams/b6f7e8a0cb32f33a4ae2bbec33dd452d.png",
            "Match Title": "Sheffield Sharks VS Surrey 89ers | SLB",
            "Match Poster": "https://placehold.co/800x450/ffffff/000000.png?text=Sheffield%20Sharks%0AVS%0ASurrey%2089ers%0ASLB&font=Oswald",
            "Match Status": "Upcoming",
            "Start Time": "9:00 PM 29-03-2026",
            "User-Agent": "Mozilla/5.0 (Linux; Android 10; K) AppleWebKit/537.36 (KHTML, like Gecko) Chrome/120.0.0.0 Mobile Safari/537.36",
            "Referer": "https://api2.ifnewgen.xyz/",
            "Stream URL": ""
        },
        {
            "Category": "Basketball",
            "League": "SLB",
            "Team 1 Name": "Cheshire Phoenix",
            "Team 2 Name": "Bristol Flyers",
            "Team 1 Logo": "https://static-live.linewgen.xyz/live/bing/img/teams/955ea10017a9491d67d57fcfe9ae77f6.png",
            "Team 2 Logo": "https://static-live.linewgen.xyz/live/bing/img/teams/3b35cee610557eff62290c7df654a1d2.png",
            "Match Title": "Cheshire Phoenix VS Bristol Flyers | SLB",
            "Match Poster": "https://placehold.co/800x450/ffffff/000000.png?text=Cheshire%20Phoenix%0AVS%0ABristol%20Flyers%0ASLB&font=Oswald",
            "Match Status": "Upcoming",
            "Start Time": "10:30 PM 29-03-2026",
            "User-Agent": "Mozilla/5.0 (Linux; Android 10; K) AppleWebKit/537.36 (KHTML, like Gecko) Chrome/120.0.0.0 Mobile Safari/537.36",
            "Referer": "https://api2.ifnewgen.xyz/",
            "Stream URL": ""
        },
        {
            "Category": "Baseball",
            "League": "NPB",
            "Team 1 Name": "Fukuoka SoftBank Hawks",
            "Team 2 Name": "Hokkaido Nippon-Ham Fighters",
            "Team 1 Logo": "https://static-live.linewgen.xyz/live/bing/img/teams/711743b3437e10f4fe95736e0035a3b8.png",
            "Team 2 Logo": "https://static-live.linewgen.xyz/live/bing/img/teams/329405cfcfea53d121091a4bee27b860.png",
            "Match Title": "Fukuoka SoftBank Hawks VS Hokkaido Nippon-Ham Fighters | NPB",
            "Match Poster": "https://placehold.co/800x450/ffffff/000000.png?text=Fukuoka%20SoftBank%20Hawks%0AVS%0AHokkaido%20Nippon-Ham%20Fighters%0ANPB&font=Oswald",
            "Match Status": "Upcoming",
            "Start Time": "10:00 AM 29-03-2026",
            "User-Agent": "Mozilla/5.0 (Linux; Android 10; K) AppleWebKit/537.36 (KHTML, like Gecko) Chrome/120.0.0.0 Mobile Safari/537.36",
            "Referer": "https://api2.ifnewgen.xyz/",
            "Stream URL": ""
        },
        {
            "Category": "Baseball",
            "League": "NPB",
            "Team 1 Name": "ORIX Buffaloes",
            "Team 2 Name": "Tohoku Rakuten Golden Eagles",
            "Team 1 Logo": "https://static-live.linewgen.xyz/live/bing/img/teams/152af9ee913c91f59154eaf2ae51db2f.png",
            "Team 2 Logo": "https://static-live.linewgen.xyz/live/bing/img/teams/ff94d5b4cc5dabc1ae07e3ff3efdfacf.png",
            "Match Title": "ORIX Buffaloes VS Tohoku Rakuten Golden Eagles | NPB",
            "Match Poster": "https://placehold.co/800x450/ffffff/000000.png?text=ORIX%20Buffaloes%0AVS%0ATohoku%20Rakuten%20Golden%20Eagles%0ANPB&font=Oswald",
            "Match Status": "Upcoming",
            "Start Time": "10:00 AM 29-03-2026",
            "User-Agent": "Mozilla/5.0 (Linux; Android 10; K) AppleWebKit/537.36 (KHTML, like Gecko) Chrome/120.0.0.0 Mobile Safari/537.36",
            "Referer": "https://api2.ifnewgen.xyz/",
            "Stream URL": ""
        },
        {
            "Category": "Baseball",
            "League": "NPB",
            "Team 1 Name": "Yomiuri Giants",
            "Team 2 Name": "Hanshin Tigers",
            "Team 1 Logo": "https://static-live.linewgen.xyz/live/bing/img/teams/9f2a207ed77e5f3e2f438e501a13c005.png",
            "Team 2 Logo": "https://static-live.linewgen.xyz/live/bing/img/teams/5a915504baf84e88cbc763dfcfc934cf.png",
            "Match Title": "Yomiuri Giants VS Hanshin Tigers | NPB",
            "Match Poster": "https://placehold.co/800x450/ffffff/000000.png?text=Yomiuri%20Giants%0AVS%0AHanshin%20Tigers%0ANPB&font=Oswald",
            "Match Status": "Upcoming",
            "Start Time": "11:00 AM 29-03-2026",
            "User-Agent": "Mozilla/5.0 (Linux; Android 10; K) AppleWebKit/537.36 (KHTML, like Gecko) Chrome/120.0.0.0 Mobile Safari/537.36",
            "Referer": "https://api2.ifnewgen.xyz/",
            "Stream URL": ""
        },
        {
            "Category": "Auto Racing",
            "League": "Formula 1",
            "Team 1 Name": "",
            "Team 2 Name": "",
            "Team 1 Logo": "",
            "Team 2 Logo": "",
            "Match Title": "JAPANESE GRAND PRIX 2026 | Formula 1",
            "Match Poster": "https://placehold.co/800x450/ffffff/000000.png?text=JAPANESE%20GRAND%20PRIX%202026%0AFormula%201&font=Oswald",
            "Match Status": "Upcoming",
            "Start Time": "9:30 AM 29-03-2026",
            "User-Agent": "Mozilla/5.0 (Linux; Android 10; K) AppleWebKit/537.36 (KHTML, like Gecko) Chrome/120.0.0.0 Mobile Safari/537.36",
            "Referer": "https://api2.ifnewgen.xyz/",
            "Stream URL": ""
        },
        {
            "Category": "Auto Racing",
            "League": "Formula 1 Main Race",
            "Team 1 Name": "",
            "Team 2 Name": "",
            "Team 1 Logo": "",
            "Team 2 Logo": "",
            "Match Title": "JAPANESE GRAND PRIX 2026 | Formula 1 Main Race",
            "Match Poster": "https://placehold.co/800x450/ffffff/000000.png?text=JAPANESE%20GRAND%20PRIX%202026%0AFormula%201%20Main%20Race&font=Oswald",
            "Match Status": "Upcoming",
            "Start Time": "10:55 AM 29-03-2026",
            "User-Agent": "Mozilla/5.0 (Linux; Android 10; K) AppleWebKit/537.36 (KHTML, like Gecko) Chrome/120.0.0.0 Mobile Safari/537.36",
            "Referer": "https://api2.ifnewgen.xyz/",
            "Stream URL": ""
        },
        {
            "Category": "Auto Racing",
            "League": "MXGP",
            "Team 1 Name": "",
            "Team 2 Name": "",
            "Team 1 Logo": "",
            "Team 2 Logo": "",
            "Match Title": "Race Day Part 1: Switzerland | MXGP",
            "Match Poster": "https://placehold.co/800x450/ffffff/000000.png?text=Race%20Day%20Part%201%3A%20Switzerland%0AMXGP&font=Oswald",
            "Match Status": "Upcoming",
            "Start Time": "6:00 PM 29-03-2026",
            "User-Agent": "Mozilla/5.0 (Linux; Android 10; K) AppleWebKit/537.36 (KHTML, like Gecko) Chrome/120.0.0.0 Mobile Safari/537.36",
            "Referer": "https://api2.ifnewgen.xyz/",
            "Stream URL": ""
        },
        {
            "Category": "MMA",
            "League": "UFC FIGHT NIGHT",
            "Team 1 Name": "",
            "Team 2 Name": "",
            "Team 1 Logo": "",
            "Team 2 Logo": "",
            "Match Title": "ADESANYA VS PYFER | UFC FIGHT NIGHT",
            "Match Poster": "https://placehold.co/800x450/ffffff/000000.png?text=ADESANYA%0AVS%0APYFER%0AUFC%20FIGHT%20NIGHT&font=Oswald",
            "Match Status": "Upcoming",
            "Start Time": "6:00 AM 29-03-2026",
            "User-Agent": "Mozilla/5.0 (Linux; Android 10; K) AppleWebKit/537.36 (KHTML, like Gecko) Chrome/120.0.0.0 Mobile Safari/537.36",
            "Referer": "https://api2.ifnewgen.xyz/",
            "Stream URL": ""
        },
        {
            "Category": "Rugby",
            "League": "PREM Rugby",
            "Team 1 Name": "Sale Sharks",
            "Team 2 Name": "Bath Rugby",
            "Team 1 Logo": "https://static-live.linewgen.xyz/live/bing/img/teams/2718bea36c841faab96584f5f73cfa0b.png",
            "Team 2 Logo": "https://static-live.linewgen.xyz/live/bing/img/teams/7fecd3d2a51e43d8ce4facf0fecc67c8.png",
            "Match Title": "Sale Sharks VS Bath Rugby | PREM Rugby",
            "Match Poster": "https://placehold.co/800x450/ffffff/000000.png?text=Sale%20Sharks%0AVS%0ABath%20Rugby%0APREM%20Rugby&font=Oswald",
            "Match Status": "Upcoming",
            "Start Time": "8:00 PM 29-03-2026",
            "User-Agent": "Mozilla/5.0 (Linux; Android 10; K) AppleWebKit/537.36 (KHTML, like Gecko) Chrome/120.0.0.0 Mobile Safari/537.36",
            "Referer": "https://api2.ifnewgen.xyz/",
            "Stream URL": ""
        }
    ]
}