{
    "playlist_info": {
        "name": "Bingstream Auto Update Playlist",
        "telegram": "https://t.me/livesportsplay",
        "owner": "Md Sohanur Rahman Hady",
        "last_update_time": "12:01:29 PM 30-06-2026"
    },
    "special_note": "If the stream does not play, please make sure to include the referer link with it.",
    "channels": [
        {
            "Category": "NPB Farm Leagues",
            "League": "NPB Farm Leagues",
            "Team 1 Name": "Tokyo Yakult Swallows",
            "Team 2 Name": "Yomiuri Giants",
            "Team 1 Logo": "https://static-live.linewgen.xyz/live/bing/img/teams/34593265410a4efe76ac3463f92c902a.png",
            "Team 2 Logo": "https://static-live.linewgen.xyz/live/bing/img/teams/9f2a207ed77e5f3e2f438e501a13c005.png",
            "Match Title": "Tokyo Yakult Swallows VS Yomiuri Giants | NPB Farm Leagues",
            "Match Poster": "https://static.vecteezy.com/system/resources/previews/016/314/808/original/transparent-live-transparent-live-icon-free-png.png",
            "Match Status": "Live",
            "Start Time": "Live Now",
            "User-Agent": "Mozilla/5.0 (Linux; Android 10; K) AppleWebKit/537.36 (KHTML, like Gecko) Chrome/120.0.0.0 Mobile Safari/537.36",
            "Referer": "https://iframe.rumsport10.live/",
            "Stream URL": [
                {
                    "server_name": "Server 1",
                    "play_url": "https://livecdn-tc-livestream.rumsport10.live/stream/20/chunks.m3u8?is_vip=false&token=1782885692-Kv4cPTAAP5YTi-dbea9bd8c94989c40e6a5d62dfcf986413c823c9-af46f80d79bb04d40de72f363bbacaa9"
                },
                {
                    "server_name": "Server 2",
                    "play_url": "https://livecdn-bp-livestream.rumsport7.live/stream/20/chunks.m3u8?is_vip=false&token=dbea9bd8c94989c40e6a5d62dfcf986413c823c9&x-sign=0cecffc5fdce42d0b5d7ab9260e37c10&x-time=1782799260"
                }
            ]
        },
        {
            "Category": "M25 Figueira da Foz",
            "League": "M25 Figueira da Foz",
            "Team 1 Name": "Emile Hudd",
            "Team 2 Name": "Francisco Rocha",
            "Team 1 Logo": "https://img.bingstream.info/static/common/thumbs/soccer/team_placeholder_45x45.png",
            "Team 2 Logo": "https://img.bingstream.info/static/common/thumbs/soccer/team_placeholder_45x45.png",
            "Match Title": "Emile Hudd VS Francisco Rocha | M25 Figueira da Foz",
            "Match Poster": "https://static.vecteezy.com/system/resources/previews/016/314/808/original/transparent-live-transparent-live-icon-free-png.png",
            "Match Status": "Live",
            "Start Time": "Live Now",
            "User-Agent": "Mozilla/5.0 (Linux; Android 10; K) AppleWebKit/537.36 (KHTML, like Gecko) Chrome/120.0.0.0 Mobile Safari/537.36",
            "Referer": "https://iframe.rumsport10.live/",
            "Stream URL": [
                {
                    "server_name": "Server 1",
                    "play_url": "https://livecdn-bp-livestream.rumsport10.live/sla/13-6a433fbad8b0af885e3cc01e/chunks.m3u8?is_vip=false&token=dbea9bd8c94989c40e6a5d62dfcf986413c823c9&x-sign=34968c920bebcff172cef970c2575545&x-time=1782799260"
                },
                {
                    "server_name": "Server 2",
                    "play_url": "https://livecdn-tc-livestream.rumsport10.live/sla/13-6a433fbad8b0af885e3cc01e/chunks.m3u8?is_vip=false&token=1782885698-Kv4cPTAAP5YTi-dbea9bd8c94989c40e6a5d62dfcf986413c823c9-4655da05274af3c43dc9246e1f7dad0d"
                }
            ]
        },
        {
            "Category": "M25 Ajaccio",
            "League": "M25 Ajaccio",
            "Team 1 Name": "Luc Fomba",
            "Team 2 Name": "Alexandre Reco",
            "Team 1 Logo": "https://img.bingstream.info/static/common/thumbs/soccer/team_placeholder_45x45.png",
            "Team 2 Logo": "https://img.bingstream.info/static/common/thumbs/soccer/team_placeholder_45x45.png",
            "Match Title": "Luc Fomba VS Alexandre Reco | M25 Ajaccio",
            "Match Poster": "https://static.vecteezy.com/system/resources/previews/016/314/808/original/transparent-live-transparent-live-icon-free-png.png",
            "Match Status": "Live",
            "Start Time": "Live Now",
            "User-Agent": "Mozilla/5.0 (Linux; Android 10; K) AppleWebKit/537.36 (KHTML, like Gecko) Chrome/120.0.0.0 Mobile Safari/537.36",
            "Referer": "https://iframe.rumsport10.live/",
            "Stream URL": [
                {
                    "server_name": "Server 1",
                    "play_url": "https://livecdn-bp-livestream.rumsport10.live/sla/13-6a433fbabb875b4ddf463fb0/chunks.m3u8?is_vip=false&token=dbea9bd8c94989c40e6a5d62dfcf986413c823c9&x-sign=adc69ea9ee000421e9642eb0a076a041&x-time=1782799260"
                },
                {
                    "server_name": "Server 2",
                    "play_url": "https://livecdn-tc-livestream.rumsport10.live/sla/13-6a433fbabb875b4ddf463fb0/chunks.m3u8?is_vip=false&token=1782885703-Kv4cPTAAP5YTi-dbea9bd8c94989c40e6a5d62dfcf986413c823c9-4dab092ee2aee9af2565a06a3c532e84"
                }
            ]
        },
        {
            "Category": "M25 Figueira da Foz",
            "League": "M25 Figueira da Foz",
            "Team 1 Name": "Rodrigo Leal",
            "Team 2 Name": "Joao Portugal",
            "Team 1 Logo": "https://img.bingstream.info/static/common/thumbs/soccer/team_placeholder_45x45.png",
            "Team 2 Logo": "https://img.bingstream.info/static/common/thumbs/soccer/team_placeholder_45x45.png",
            "Match Title": "Rodrigo Leal VS Joao Portugal | M25 Figueira da Foz",
            "Match Poster": "https://static.vecteezy.com/system/resources/previews/016/314/808/original/transparent-live-transparent-live-icon-free-png.png",
            "Match Status": "Live",
            "Start Time": "Live Now",
            "User-Agent": "Mozilla/5.0 (Linux; Android 10; K) AppleWebKit/537.36 (KHTML, like Gecko) Chrome/120.0.0.0 Mobile Safari/537.36",
            "Referer": "https://iframe.rumsport10.live/",
            "Stream URL": [
                {
                    "server_name": "Server 1",
                    "play_url": "https://livecdn-bp-livestream.rumsport10.live/sla/13-6a433fbabb875b4ddf463fb1/chunks.m3u8?is_vip=false&token=dbea9bd8c94989c40e6a5d62dfcf986413c823c9&x-sign=fbfedfee33a5490e8af091d8a218b4b9&x-time=1782799260"
                },
                {
                    "server_name": "Server 2",
                    "play_url": "https://livecdn-tc-livestream.rumsport10.live/sla/13-6a433fbabb875b4ddf463fb1/chunks.m3u8?is_vip=false&token=1782885708-Kv4cPTAAP5YTi-dbea9bd8c94989c40e6a5d62dfcf986413c823c9-041eaa519b4550b9bfd9883fcee32502"
                }
            ]
        },
        {
            "Category": "M25 Figueira da Foz",
            "League": "M25 Figueira da Foz",
            "Team 1 Name": "Goncalo Marques",
            "Team 2 Name": "Maxwell McKennon",
            "Team 1 Logo": "https://img.bingstream.info/static/common/thumbs/soccer/team_placeholder_45x45.png",
            "Team 2 Logo": "https://img.bingstream.info/static/common/thumbs/soccer/team_placeholder_45x45.png",
            "Match Title": "Goncalo Marques VS Maxwell McKennon | M25 Figueira da Foz",
            "Match Poster": "https://static.vecteezy.com/system/resources/previews/016/314/808/original/transparent-live-transparent-live-icon-free-png.png",
            "Match Status": "Live",
            "Start Time": "Live Now",
            "User-Agent": "Mozilla/5.0 (Linux; Android 10; K) AppleWebKit/537.36 (KHTML, like Gecko) Chrome/120.0.0.0 Mobile Safari/537.36",
            "Referer": "https://iframe.rumsport10.live/",
            "Stream URL": [
                {
                    "server_name": "Server 1",
                    "play_url": "https://livecdn-bp-livestream.rumsport10.live/sla/13-6a433fbaa536306159af4f5a/chunks.m3u8?is_vip=false&token=dbea9bd8c94989c40e6a5d62dfcf986413c823c9&x-sign=1e4088c19359175b64aa68199f9ffe70&x-time=1782799260"
                },
                {
                    "server_name": "Server 2",
                    "play_url": "https://livecdn-tc-livestream.rumsport10.live/sla/13-6a433fbaa536306159af4f5a/chunks.m3u8?is_vip=false&token=1782885713-Kv4cPTAAP5YTi-dbea9bd8c94989c40e6a5d62dfcf986413c823c9-346eee6fc6922751ff9840807950cb3c"
                }
            ]
        },
        {
            "Category": "M25 Ajaccio",
            "League": "M25 Ajaccio",
            "Team 1 Name": "Tanguy Genier",
            "Team 2 Name": "Arthur Bonnaud",
            "Team 1 Logo": "https://img.bingstream.info/static/common/thumbs/soccer/team_placeholder_45x45.png",
            "Team 2 Logo": "https://img.bingstream.info/static/common/thumbs/soccer/team_placeholder_45x45.png",
            "Match Title": "Tanguy Genier VS Arthur Bonnaud | M25 Ajaccio",
            "Match Poster": "https://static.vecteezy.com/system/resources/previews/016/314/808/original/transparent-live-transparent-live-icon-free-png.png",
            "Match Status": "Live",
            "Start Time": "Live Now",
            "User-Agent": "Mozilla/5.0 (Linux; Android 10; K) AppleWebKit/537.36 (KHTML, like Gecko) Chrome/120.0.0.0 Mobile Safari/537.36",
            "Referer": "https://iframe.rumsport10.live/",
            "Stream URL": [
                {
                    "server_name": "Server 1",
                    "play_url": "https://livecdn-bp-livestream.rumsport10.live/sla/13-6a433fba32c497f673700e18/chunks.m3u8?is_vip=false&token=dbea9bd8c94989c40e6a5d62dfcf986413c823c9&x-sign=7611d7fa7743a72f6177e530fc0f370d&x-time=1782799260"
                },
                {
                    "server_name": "Server 2",
                    "play_url": "https://livecdn-tc-livestream.rumsport10.live/sla/13-6a433fba32c497f673700e18/chunks.m3u8?is_vip=false&token=1782885718-Kv4cPTAAP5YTi-dbea9bd8c94989c40e6a5d62dfcf986413c823c9-07aaebb928e2d884505d730dba4205b1"
                }
            ]
        },
        {
            "Category": "M25 Figueira da Foz",
            "League": "M25 Figueira da Foz",
            "Team 1 Name": "Rohan Mehra",
            "Team 2 Name": "Daniil Ostapenkov",
            "Team 1 Logo": "https://img.bingstream.info/static/common/thumbs/soccer/team_placeholder_45x45.png",
            "Team 2 Logo": "https://img.bingstream.info/static/common/thumbs/soccer/team_placeholder_45x45.png",
            "Match Title": "Rohan Mehra VS Daniil Ostapenkov | M25 Figueira da Foz",
            "Match Poster": "https://static.vecteezy.com/system/resources/previews/016/314/808/original/transparent-live-transparent-live-icon-free-png.png",
            "Match Status": "Live",
            "Start Time": "Live Now",
            "User-Agent": "Mozilla/5.0 (Linux; Android 10; K) AppleWebKit/537.36 (KHTML, like Gecko) Chrome/120.0.0.0 Mobile Safari/537.36",
            "Referer": "https://iframe.rumsport10.live/",
            "Stream URL": [
                {
                    "server_name": "Server 1",
                    "play_url": "https://livecdn-bp-livestream.rumsport10.live/sla/13-6a433fba6618c8c6843db966/chunks.m3u8?is_vip=false&token=dbea9bd8c94989c40e6a5d62dfcf986413c823c9&x-sign=1a62b687d32c342d92656251d84045d0&x-time=1782799320"
                },
                {
                    "server_name": "Server 2",
                    "play_url": "https://livecdn-tc-livestream.rumsport10.live/sla/13-6a433fba6618c8c6843db966/chunks.m3u8?is_vip=false&token=1782885723-Kv4cPTAAP5YTi-dbea9bd8c94989c40e6a5d62dfcf986413c823c9-b23c03f1dd44427e935fa2e1f999f795"
                }
            ]
        },
        {
            "Category": "M15 Getxo MD",
            "League": "M15 Getxo MD",
            "Team 1 Name": "Alvarez Sarmiento/Garcia Carbajal",
            "Team 2 Name": "Martinez/Meneses Perny",
            "Team 1 Logo": "https://img.bingstream.info/static/common/thumbs/soccer/team_placeholder_45x45.png",
            "Team 2 Logo": "https://img.bingstream.info/static/common/thumbs/soccer/team_placeholder_45x45.png",
            "Match Title": "Alvarez Sarmiento/Garcia Carbajal VS Martinez/Meneses Perny | M15 Getxo MD",
            "Match Poster": "https://static.vecteezy.com/system/resources/previews/016/314/808/original/transparent-live-transparent-live-icon-free-png.png",
            "Match Status": "Live",
            "Start Time": "Live Now",
            "User-Agent": "Mozilla/5.0 (Linux; Android 10; K) AppleWebKit/537.36 (KHTML, like Gecko) Chrome/120.0.0.0 Mobile Safari/537.36",
            "Referer": "https://iframe.rumsport10.live/",
            "Stream URL": [
                {
                    "server_name": "Server 1",
                    "play_url": "https://livecdn-bp-livestream.rumsport10.live/sla/13-6a433fba4b4d858b85c3d4f9/chunks.m3u8?is_vip=false&token=dbea9bd8c94989c40e6a5d62dfcf986413c823c9&x-sign=1ff4e271d0f38da07753d6d8b1a1adaf&x-time=1782799320"
                },
                {
                    "server_name": "Server 2",
                    "play_url": "https://livecdn-tc-livestream.rumsport10.live/sla/13-6a433fba4b4d858b85c3d4f9/chunks.m3u8?is_vip=false&token=1782885727-Kv4cPTAAP5YTi-dbea9bd8c94989c40e6a5d62dfcf986413c823c9-3649db4a87bb94f0b3756da4f1bd5ae6"
                }
            ]
        },
        {
            "Category": "M15 Getxo MD",
            "League": "M15 Getxo MD",
            "Team 1 Name": "Garcia Mestre/Naharro",
            "Team 2 Name": "Arce Fernandez/Talavera Cortes",
            "Team 1 Logo": "https://img.bingstream.info/static/common/thumbs/soccer/team_placeholder_45x45.png",
            "Team 2 Logo": "https://img.bingstream.info/static/common/thumbs/soccer/team_placeholder_45x45.png",
            "Match Title": "Garcia Mestre/Naharro VS Arce Fernandez/Talavera Cortes | M15 Getxo MD",
            "Match Poster": "https://static.vecteezy.com/system/resources/previews/016/314/808/original/transparent-live-transparent-live-icon-free-png.png",
            "Match Status": "Live",
            "Start Time": "Live Now",
            "User-Agent": "Mozilla/5.0 (Linux; Android 10; K) AppleWebKit/537.36 (KHTML, like Gecko) Chrome/120.0.0.0 Mobile Safari/537.36",
            "Referer": "https://iframe.rumsport10.live/",
            "Stream URL": [
                {
                    "server_name": "Server 1",
                    "play_url": "https://livecdn-bp-livestream.rumsport10.live/sla/13-6a433fba8cf75300576e9329/chunks.m3u8?is_vip=false&token=dbea9bd8c94989c40e6a5d62dfcf986413c823c9&x-sign=8fe2ec14d6ac65759a2f554179b163e3&x-time=1782799320"
                },
                {
                    "server_name": "Server 2",
                    "play_url": "https://livecdn-tc-livestream.rumsport10.live/sla/13-6a433fba8cf75300576e9329/chunks.m3u8?is_vip=false&token=1782885732-Kv4cPTAAP5YTi-dbea9bd8c94989c40e6a5d62dfcf986413c823c9-ae2dce8f9ef0c751f72ad60a82567c23"
                }
            ]
        },
        {
            "Category": "M25 Ajaccio",
            "League": "M25 Ajaccio",
            "Team 1 Name": "Robin Catry",
            "Team 2 Name": "Mikail Alimli",
            "Team 1 Logo": "https://img.bingstream.info/static/common/thumbs/soccer/team_placeholder_45x45.png",
            "Team 2 Logo": "https://img.bingstream.info/static/common/thumbs/soccer/team_placeholder_45x45.png",
            "Match Title": "Robin Catry VS Mikail Alimli | M25 Ajaccio",
            "Match Poster": "https://static.vecteezy.com/system/resources/previews/016/314/808/original/transparent-live-transparent-live-icon-free-png.png",
            "Match Status": "Live",
            "Start Time": "Live Now",
            "User-Agent": "Mozilla/5.0 (Linux; Android 10; K) AppleWebKit/537.36 (KHTML, like Gecko) Chrome/120.0.0.0 Mobile Safari/537.36",
            "Referer": "https://iframe.rumsport10.live/",
            "Stream URL": [
                {
                    "server_name": "Server 1",
                    "play_url": "https://livecdn-bp-livestream.rumsport10.live/sla/13-6a433fba945e9dbcc7a2776e/chunks.m3u8?is_vip=false&token=dbea9bd8c94989c40e6a5d62dfcf986413c823c9&x-sign=1175ebc8716053473f77b761a759bd8d&x-time=1782799320"
                },
                {
                    "server_name": "Server 2",
                    "play_url": "https://livecdn-tc-livestream.rumsport10.live/sla/13-6a433fba945e9dbcc7a2776e/chunks.m3u8?is_vip=false&token=1782885737-Kv4cPTAAP5YTi-dbea9bd8c94989c40e6a5d62dfcf986413c823c9-4ea952dd8a8d5909541c2a414ba525d4"
                }
            ]
        },
        {
            "Category": "M25 Figueira da Foz",
            "League": "M25 Figueira da Foz",
            "Team 1 Name": "Karan Singh",
            "Team 2 Name": "Tiago Cacao",
            "Team 1 Logo": "https://img.bingstream.info/static/common/thumbs/soccer/team_placeholder_45x45.png",
            "Team 2 Logo": "https://img.bingstream.info/static/common/thumbs/soccer/team_placeholder_45x45.png",
            "Match Title": "Karan Singh VS Tiago Cacao | M25 Figueira da Foz",
            "Match Poster": "https://static.vecteezy.com/system/resources/previews/016/314/808/original/transparent-live-transparent-live-icon-free-png.png",
            "Match Status": "Live",
            "Start Time": "Live Now",
            "User-Agent": "Mozilla/5.0 (Linux; Android 10; K) AppleWebKit/537.36 (KHTML, like Gecko) Chrome/120.0.0.0 Mobile Safari/537.36",
            "Referer": "https://iframe.rumsport10.live/",
            "Stream URL": [
                {
                    "server_name": "Server 1",
                    "play_url": "https://livecdn-bp-livestream.rumsport10.live/sla/13-6a433fba4b4d858b85c3d4f7/chunks.m3u8?is_vip=false&token=dbea9bd8c94989c40e6a5d62dfcf986413c823c9&x-sign=7cd77e0bb1e78de1097133776c47a7ca&x-time=1782799320"
                },
                {
                    "server_name": "Server 2",
                    "play_url": "https://livecdn-tc-livestream.rumsport10.live/sla/13-6a433fba4b4d858b85c3d4f7/chunks.m3u8?is_vip=false&token=1782885742-Kv4cPTAAP5YTi-dbea9bd8c94989c40e6a5d62dfcf986413c823c9-2b0193e1d3078611e58700d5a4208ac3"
                }
            ]
        },
        {
            "Category": "M25 Ajaccio",
            "League": "M25 Ajaccio",
            "Team 1 Name": "Peter Buldorini",
            "Team 2 Name": "Benjamin Pietri",
            "Team 1 Logo": "https://img.bingstream.info/static/common/thumbs/soccer/team_placeholder_45x45.png",
            "Team 2 Logo": "https://img.bingstream.info/static/common/thumbs/soccer/team_placeholder_45x45.png",
            "Match Title": "Peter Buldorini VS Benjamin Pietri | M25 Ajaccio",
            "Match Poster": "https://static.vecteezy.com/system/resources/previews/016/314/808/original/transparent-live-transparent-live-icon-free-png.png",
            "Match Status": "Live",
            "Start Time": "Live Now",
            "User-Agent": "Mozilla/5.0 (Linux; Android 10; K) AppleWebKit/537.36 (KHTML, like Gecko) Chrome/120.0.0.0 Mobile Safari/537.36",
            "Referer": "https://iframe.rumsport10.live/",
            "Stream URL": [
                {
                    "server_name": "Server 1",
                    "play_url": "https://livecdn-bp-livestream.rumsport10.live/sla/13-6a433fba32c497f673700e19/chunks.m3u8?is_vip=false&token=dbea9bd8c94989c40e6a5d62dfcf986413c823c9&x-sign=de20bdf12545b73df45de9ada8130eab&x-time=1782799320"
                },
                {
                    "server_name": "Server 2",
                    "play_url": "https://livecdn-tc-livestream.rumsport10.live/sla/13-6a433fba32c497f673700e19/chunks.m3u8?is_vip=false&token=1782885747-Kv4cPTAAP5YTi-dbea9bd8c94989c40e6a5d62dfcf986413c823c9-2dd1b96d4a66355d1f3c02f284d427ec"
                }
            ]
        },
        {
            "Category": "M25 Marburg",
            "League": "M25 Marburg",
            "Team 1 Name": "Imanol Lopez Morillo",
            "Team 2 Name": "Calvin Mueller",
            "Team 1 Logo": "https://img.bingstream.info/static/common/thumbs/soccer/team_placeholder_45x45.png",
            "Team 2 Logo": "https://img.bingstream.info/static/common/thumbs/soccer/team_placeholder_45x45.png",
            "Match Title": "Imanol Lopez Morillo VS Calvin Mueller | M25 Marburg",
            "Match Poster": "https://static.vecteezy.com/system/resources/previews/016/314/808/original/transparent-live-transparent-live-icon-free-png.png",
            "Match Status": "Live",
            "Start Time": "Live Now",
            "User-Agent": "Mozilla/5.0 (Linux; Android 10; K) AppleWebKit/537.36 (KHTML, like Gecko) Chrome/120.0.0.0 Mobile Safari/537.36",
            "Referer": "https://iframe.rumsport10.live/",
            "Stream URL": [
                {
                    "server_name": "Server 1",
                    "play_url": "https://livecdn-bp-livestream.rumsport10.live/sla/13-6a433fbabb875b4ddf463faf/chunks.m3u8?is_vip=false&token=dbea9bd8c94989c40e6a5d62dfcf986413c823c9&x-sign=c4a7550f0193de6830f2fc49f07ed4db&x-time=1782799320"
                },
                {
                    "server_name": "Server 2",
                    "play_url": "https://livecdn-tc-livestream.rumsport10.live/sla/13-6a433fbabb875b4ddf463faf/chunks.m3u8?is_vip=false&token=1782885752-Kv4cPTAAP5YTi-dbea9bd8c94989c40e6a5d62dfcf986413c823c9-74caa2bfcd9d37d8672a8be907497f73"
                }
            ]
        },
        {
            "Category": "M25 Ajaccio",
            "League": "M25 Ajaccio",
            "Team 1 Name": "Louis Larue",
            "Team 2 Name": "Laurent Lokoli",
            "Team 1 Logo": "https://img.bingstream.info/static/common/thumbs/soccer/team_placeholder_45x45.png",
            "Team 2 Logo": "https://img.bingstream.info/static/common/thumbs/soccer/team_placeholder_45x45.png",
            "Match Title": "Louis Larue VS Laurent Lokoli | M25 Ajaccio",
            "Match Poster": "https://static.vecteezy.com/system/resources/previews/016/314/808/original/transparent-live-transparent-live-icon-free-png.png",
            "Match Status": "Live",
            "Start Time": "Live Now",
            "User-Agent": "Mozilla/5.0 (Linux; Android 10; K) AppleWebKit/537.36 (KHTML, like Gecko) Chrome/120.0.0.0 Mobile Safari/537.36",
            "Referer": "https://iframe.rumsport10.live/",
            "Stream URL": [
                {
                    "server_name": "Server 1",
                    "play_url": "https://livecdn-bp-livestream.rumsport10.live/sla/13-6a433fbabb875b4ddf463fb2/chunks.m3u8?is_vip=false&token=dbea9bd8c94989c40e6a5d62dfcf986413c823c9&x-sign=dbb62b2a2c93881262195c2f441a875d&x-time=1782799320"
                },
                {
                    "server_name": "Server 2",
                    "play_url": "https://livecdn-tc-livestream.rumsport10.live/sla/13-6a433fbabb875b4ddf463fb2/chunks.m3u8?is_vip=false&token=1782885757-Kv4cPTAAP5YTi-dbea9bd8c94989c40e6a5d62dfcf986413c823c9-edb6a087fe7ac779ddf6bd83d7af1594"
                }
            ]
        },
        {
            "Category": "M25 Ajaccio",
            "League": "M25 Ajaccio",
            "Team 1 Name": "Hugo Grenier",
            "Team 2 Name": "Tristan Berard",
            "Team 1 Logo": "https://img.bingstream.info/static/common/thumbs/soccer/team_placeholder_45x45.png",
            "Team 2 Logo": "https://img.bingstream.info/static/common/thumbs/soccer/team_placeholder_45x45.png",
            "Match Title": "Hugo Grenier VS Tristan Berard | M25 Ajaccio",
            "Match Poster": "https://static.vecteezy.com/system/resources/previews/016/314/808/original/transparent-live-transparent-live-icon-free-png.png",
            "Match Status": "Live",
            "Start Time": "Live Now",
            "User-Agent": "Mozilla/5.0 (Linux; Android 10; K) AppleWebKit/537.36 (KHTML, like Gecko) Chrome/120.0.0.0 Mobile Safari/537.36",
            "Referer": "https://iframe.rumsport10.live/",
            "Stream URL": [
                {
                    "server_name": "Server 1",
                    "play_url": "https://livecdn-bp-livestream.rumsport10.live/sla/13-6a433fba4b4d858b85c3d4f8/chunks.m3u8?is_vip=false&token=dbea9bd8c94989c40e6a5d62dfcf986413c823c9&x-sign=9863a05f4feb2babe38ffc36492e44e4&x-time=1782799320"
                },
                {
                    "server_name": "Server 2",
                    "play_url": "https://livecdn-tc-livestream.rumsport10.live/sla/13-6a433fba4b4d858b85c3d4f8/chunks.m3u8?is_vip=false&token=1782885762-Kv4cPTAAP5YTi-dbea9bd8c94989c40e6a5d62dfcf986413c823c9-0ab9b78a81f176367b701bf83675e624"
                }
            ]
        },
        {
            "Category": "W50 Elvas",
            "League": "W50 Elvas",
            "Team 1 Name": "Angelina Voloshchuk",
            "Team 2 Name": "Carmen Gallardo Guevara",
            "Team 1 Logo": "https://img.bingstream.info/static/common/thumbs/soccer/team_placeholder_45x45.png",
            "Team 2 Logo": "https://img.bingstream.info/static/common/thumbs/soccer/team_placeholder_45x45.png",
            "Match Title": "Angelina Voloshchuk VS Carmen Gallardo Guevara | W50 Elvas",
            "Match Poster": "https://static.vecteezy.com/system/resources/previews/016/314/808/original/transparent-live-transparent-live-icon-free-png.png",
            "Match Status": "Live",
            "Start Time": "Live Now",
            "User-Agent": "Mozilla/5.0 (Linux; Android 10; K) AppleWebKit/537.36 (KHTML, like Gecko) Chrome/120.0.0.0 Mobile Safari/537.36",
            "Referer": "https://iframe.rumsport10.live/",
            "Stream URL": [
                {
                    "server_name": "Server 1",
                    "play_url": "https://livecdn-bp-livestream.rumsport10.live/sla/13-6a434dfb1ceff89491a90c76/chunks.m3u8?is_vip=false&token=dbea9bd8c94989c40e6a5d62dfcf986413c823c9&x-sign=615c5190db8c42502674eb27a1db37bd&x-time=1782799320"
                },
                {
                    "server_name": "Server 2",
                    "play_url": "https://livecdn-tc-livestream.rumsport10.live/sla/13-6a434dfb1ceff89491a90c76/chunks.m3u8?is_vip=false&token=1782885767-Kv4cPTAAP5YTi-dbea9bd8c94989c40e6a5d62dfcf986413c823c9-40104ed349a21c32c9b32c4bbbd57b5e"
                }
            ]
        },
        {
            "Category": "W50 Elvas",
            "League": "W50 Elvas",
            "Team 1 Name": "Caterina Odorizzi",
            "Team 2 Name": "Hina Inoue",
            "Team 1 Logo": "https://img.bingstream.info/static/common/thumbs/soccer/team_placeholder_45x45.png",
            "Team 2 Logo": "https://img.bingstream.info/static/common/thumbs/soccer/team_placeholder_45x45.png",
            "Match Title": "Caterina Odorizzi VS Hina Inoue | W50 Elvas",
            "Match Poster": "https://static.vecteezy.com/system/resources/previews/016/314/808/original/transparent-live-transparent-live-icon-free-png.png",
            "Match Status": "Live",
            "Start Time": "Live Now",
            "User-Agent": "Mozilla/5.0 (Linux; Android 10; K) AppleWebKit/537.36 (KHTML, like Gecko) Chrome/120.0.0.0 Mobile Safari/537.36",
            "Referer": "https://iframe.rumsport10.live/",
            "Stream URL": [
                {
                    "server_name": "Server 1",
                    "play_url": "https://livecdn-bp-livestream.rumsport10.live/sla/13-6a434dfb55d8b708a7d3bde9/chunks.m3u8?is_vip=false&token=dbea9bd8c94989c40e6a5d62dfcf986413c823c9&x-sign=0f7873d13cb2e5e50ee2aee64bf4964d&x-time=1782799320"
                },
                {
                    "server_name": "Server 2",
                    "play_url": "https://livecdn-tc-livestream.rumsport10.live/sla/13-6a434dfb55d8b708a7d3bde9/chunks.m3u8?is_vip=false&token=1782885772-Kv4cPTAAP5YTi-dbea9bd8c94989c40e6a5d62dfcf986413c823c9-95d2c2090349e210d753989166d36787"
                }
            ]
        },
        {
            "Category": "W50 Stuttgart-Vaihingen",
            "League": "W50 Stuttgart-Vaihingen",
            "Team 1 Name": "Francesca Parcelli",
            "Team 2 Name": "Michaela Bayerlova",
            "Team 1 Logo": "https://img.bingstream.info/static/common/thumbs/soccer/team_placeholder_45x45.png",
            "Team 2 Logo": "https://img.bingstream.info/static/common/thumbs/soccer/team_placeholder_45x45.png",
            "Match Title": "Francesca Parcelli VS Michaela Bayerlova | W50 Stuttgart-Vaihingen",
            "Match Poster": "https://static.vecteezy.com/system/resources/previews/016/314/808/original/transparent-live-transparent-live-icon-free-png.png",
            "Match Status": "Live",
            "Start Time": "Live Now",
            "User-Agent": "Mozilla/5.0 (Linux; Android 10; K) AppleWebKit/537.36 (KHTML, like Gecko) Chrome/120.0.0.0 Mobile Safari/537.36",
            "Referer": "https://iframe.rumsport10.live/",
            "Stream URL": [
                {
                    "server_name": "Server 1",
                    "play_url": "https://livecdn-bp-livestream.rumsport10.live/sla/13-6a434dfbf59507a97a1afcde/chunks.m3u8?is_vip=false&token=dbea9bd8c94989c40e6a5d62dfcf986413c823c9&x-sign=67fea93836b51d2697699943175457d5&x-time=1782799320"
                },
                {
                    "server_name": "Server 2",
                    "play_url": "https://livecdn-tc-livestream.rumsport10.live/sla/13-6a434dfbf59507a97a1afcde/chunks.m3u8?is_vip=false&token=1782885777-Kv4cPTAAP5YTi-dbea9bd8c94989c40e6a5d62dfcf986413c823c9-cf23835127f7306211eb0ddb12c6900f"
                }
            ]
        },
        {
            "Category": "W50 Stuttgart-Vaihingen",
            "League": "W50 Stuttgart-Vaihingen",
            "Team 1 Name": "Laima Vladson",
            "Team 2 Name": "Kailey Evans",
            "Team 1 Logo": "https://img.bingstream.info/static/common/thumbs/soccer/team_placeholder_45x45.png",
            "Team 2 Logo": "https://img.bingstream.info/static/common/thumbs/soccer/team_placeholder_45x45.png",
            "Match Title": "Laima Vladson VS Kailey Evans | W50 Stuttgart-Vaihingen",
            "Match Poster": "https://static.vecteezy.com/system/resources/previews/016/314/808/original/transparent-live-transparent-live-icon-free-png.png",
            "Match Status": "Live",
            "Start Time": "Live Now",
            "User-Agent": "Mozilla/5.0 (Linux; Android 10; K) AppleWebKit/537.36 (KHTML, like Gecko) Chrome/120.0.0.0 Mobile Safari/537.36",
            "Referer": "https://iframe.rumsport10.live/",
            "Stream URL": [
                {
                    "server_name": "Server 1",
                    "play_url": "https://livecdn-bp-livestream.rumsport10.live/sla/13-6a434dfb9a1d202ef66ca02b/chunks.m3u8?is_vip=false&token=dbea9bd8c94989c40e6a5d62dfcf986413c823c9&x-sign=29109728b75118ef62704daeb5a3c66e&x-time=1782799380"
                },
                {
                    "server_name": "Server 2",
                    "play_url": "https://livecdn-tc-livestream.rumsport10.live/sla/13-6a434dfb9a1d202ef66ca02b/chunks.m3u8?is_vip=false&token=1782885781-Kv4cPTAAP5YTi-dbea9bd8c94989c40e6a5d62dfcf986413c823c9-e67ecd717ccccc93a094f50dde614194"
                }
            ]
        },
        {
            "Category": "M15 Kursumlijska Banja MD",
            "League": "M15 Kursumlijska Banja MD",
            "Team 1 Name": "Torcq/Torres Ramis",
            "Team 2 Name": "Hamza Reguig/Jonathan Ivarsson",
            "Team 1 Logo": "https://img.bingstream.info/static/common/thumbs/soccer/team_placeholder_45x45.png",
            "Team 2 Logo": "https://img.bingstream.info/static/common/thumbs/soccer/team_placeholder_45x45.png",
            "Match Title": "Torcq/Torres Ramis VS Hamza Reguig/Jonathan Ivarsson | M15 Kursumlijska Banja MD",
            "Match Poster": "https://static.vecteezy.com/system/resources/previews/016/314/808/original/transparent-live-transparent-live-icon-free-png.png",
            "Match Status": "Live",
            "Start Time": "Live Now",
            "User-Agent": "Mozilla/5.0 (Linux; Android 10; K) AppleWebKit/537.36 (KHTML, like Gecko) Chrome/120.0.0.0 Mobile Safari/537.36",
            "Referer": "https://iframe.rumsport10.live/",
            "Stream URL": [
                {
                    "server_name": "Server 1",
                    "play_url": "https://livecdn-bp-livestream.rumsport10.live/sla/13-6a434dfbf59507a97a1afcdf/chunks.m3u8?is_vip=false&token=dbea9bd8c94989c40e6a5d62dfcf986413c823c9&x-sign=f47aac6a6953e850b4c5df8d7bd0d9e6&x-time=1782799380"
                },
                {
                    "server_name": "Server 2",
                    "play_url": "https://livecdn-tc-livestream.rumsport10.live/sla/13-6a434dfbf59507a97a1afcdf/chunks.m3u8?is_vip=false&token=1782885786-Kv4cPTAAP5YTi-dbea9bd8c94989c40e6a5d62dfcf986413c823c9-0d2f27c293d1ba7388e6ca89015ff35d"
                }
            ]
        },
        {
            "Category": "M15 Kursumlijska Banja MD",
            "League": "M15 Kursumlijska Banja MD",
            "Team 1 Name": "Pavia/Teglas",
            "Team 2 Name": "Prasievi/Ushakov",
            "Team 1 Logo": "https://img.bingstream.info/static/common/thumbs/soccer/team_placeholder_45x45.png",
            "Team 2 Logo": "https://img.bingstream.info/static/common/thumbs/soccer/team_placeholder_45x45.png",
            "Match Title": "Pavia/Teglas VS Prasievi/Ushakov | M15 Kursumlijska Banja MD",
            "Match Poster": "https://static.vecteezy.com/system/resources/previews/016/314/808/original/transparent-live-transparent-live-icon-free-png.png",
            "Match Status": "Live",
            "Start Time": "Live Now",
            "User-Agent": "Mozilla/5.0 (Linux; Android 10; K) AppleWebKit/537.36 (KHTML, like Gecko) Chrome/120.0.0.0 Mobile Safari/537.36",
            "Referer": "https://iframe.rumsport10.live/",
            "Stream URL": [
                {
                    "server_name": "Server 1",
                    "play_url": "https://livecdn-bp-livestream.rumsport10.live/sla/13-6a434dfb9a1d202ef66ca02c/chunks.m3u8?is_vip=false&token=dbea9bd8c94989c40e6a5d62dfcf986413c823c9&x-sign=1ff407a84f85f06677dccbd576104292&x-time=1782799380"
                },
                {
                    "server_name": "Server 2",
                    "play_url": "https://livecdn-tc-livestream.rumsport10.live/sla/13-6a434dfb9a1d202ef66ca02c/chunks.m3u8?is_vip=false&token=1782885791-Kv4cPTAAP5YTi-dbea9bd8c94989c40e6a5d62dfcf986413c823c9-d14169393c0af591a23bd9a5e21ff3a7"
                }
            ]
        },
        {
            "Category": "W50 Stuttgart-Vaihingen",
            "League": "W50 Stuttgart-Vaihingen",
            "Team 1 Name": "Danka Kovinic",
            "Team 2 Name": "Marie Vogt",
            "Team 1 Logo": "https://img.bingstream.info/static/common/thumbs/soccer/team_placeholder_45x45.png",
            "Team 2 Logo": "https://img.bingstream.info/static/common/thumbs/soccer/team_placeholder_45x45.png",
            "Match Title": "Danka Kovinic VS Marie Vogt | W50 Stuttgart-Vaihingen",
            "Match Poster": "https://static.vecteezy.com/system/resources/previews/016/314/808/original/transparent-live-transparent-live-icon-free-png.png",
            "Match Status": "Live",
            "Start Time": "Live Now",
            "User-Agent": "Mozilla/5.0 (Linux; Android 10; K) AppleWebKit/537.36 (KHTML, like Gecko) Chrome/120.0.0.0 Mobile Safari/537.36",
            "Referer": "https://iframe.rumsport10.live/",
            "Stream URL": [
                {
                    "server_name": "Server 1",
                    "play_url": "https://livecdn-bp-livestream.rumsport10.live/sla/13-6a434dfb818b53788c4c456d/chunks.m3u8?is_vip=false&token=dbea9bd8c94989c40e6a5d62dfcf986413c823c9&x-sign=f6841d931adedffc0da35ba06bca05ce&x-time=1782799380"
                },
                {
                    "server_name": "Server 2",
                    "play_url": "https://livecdn-tc-livestream.rumsport10.live/sla/13-6a434dfb818b53788c4c456d/chunks.m3u8?is_vip=false&token=1782885796-Kv4cPTAAP5YTi-dbea9bd8c94989c40e6a5d62dfcf986413c823c9-dec01b1fa526a3e4a757a5e7fe16cb17"
                }
            ]
        },
        {
            "Category": "W50 Stuttgart-Vaihingen WD",
            "League": "W50 Stuttgart-Vaihingen WD",
            "Team 1 Name": "Morderger/Morderger",
            "Team 2 Name": "Steiner/Stusek",
            "Team 1 Logo": "https://img.bingstream.info/static/common/thumbs/soccer/team_placeholder_45x45.png",
            "Team 2 Logo": "https://img.bingstream.info/static/common/thumbs/soccer/team_placeholder_45x45.png",
            "Match Title": "Morderger/Morderger VS Steiner/Stusek | W50 Stuttgart-Vaihingen WD",
            "Match Poster": "https://static.vecteezy.com/system/resources/previews/016/314/808/original/transparent-live-transparent-live-icon-free-png.png",
            "Match Status": "Live",
            "Start Time": "Live Now",
            "User-Agent": "Mozilla/5.0 (Linux; Android 10; K) AppleWebKit/537.36 (KHTML, like Gecko) Chrome/120.0.0.0 Mobile Safari/537.36",
            "Referer": "https://iframe.rumsport10.live/",
            "Stream URL": [
                {
                    "server_name": "Server 1",
                    "play_url": "https://livecdn-bp-livestream.rumsport10.live/sla/13-6a434dfbebc5c3ef2c982491/chunks.m3u8?is_vip=false&token=dbea9bd8c94989c40e6a5d62dfcf986413c823c9&x-sign=64bcff55553f44a402a34ee7e04eee18&x-time=1782799380"
                },
                {
                    "server_name": "Server 2",
                    "play_url": "https://livecdn-tc-livestream.rumsport10.live/sla/13-6a434dfbebc5c3ef2c982491/chunks.m3u8?is_vip=false&token=1782885801-Kv4cPTAAP5YTi-dbea9bd8c94989c40e6a5d62dfcf986413c823c9-4e94df7c78c381291237910570e40135"
                }
            ]
        },
        {
            "Category": "M25 Marburg",
            "League": "M25 Marburg",
            "Team 1 Name": "Alec Beckley",
            "Team 2 Name": "Tom Sickenberger",
            "Team 1 Logo": "https://img.bingstream.info/static/common/thumbs/soccer/team_placeholder_45x45.png",
            "Team 2 Logo": "https://img.bingstream.info/static/common/thumbs/soccer/team_placeholder_45x45.png",
            "Match Title": "Alec Beckley VS Tom Sickenberger | M25 Marburg",
            "Match Poster": "https://static.vecteezy.com/system/resources/previews/016/314/808/original/transparent-live-transparent-live-icon-free-png.png",
            "Match Status": "Live",
            "Start Time": "Live Now",
            "User-Agent": "Mozilla/5.0 (Linux; Android 10; K) AppleWebKit/537.36 (KHTML, like Gecko) Chrome/120.0.0.0 Mobile Safari/537.36",
            "Referer": "https://iframe.rumsport10.live/",
            "Stream URL": [
                {
                    "server_name": "Server 1",
                    "play_url": "https://livecdn-bp-livestream.rumsport10.live/sla/13-6a433fba4b4d858b85c3d4f6/chunks.m3u8?is_vip=false&token=dbea9bd8c94989c40e6a5d62dfcf986413c823c9&x-sign=43b2529c5988517753448b94105577e6&x-time=1782799380"
                },
                {
                    "server_name": "Server 2",
                    "play_url": "https://livecdn-tc-livestream.rumsport10.live/sla/13-6a433fba4b4d858b85c3d4f6/chunks.m3u8?is_vip=false&token=1782885806-Kv4cPTAAP5YTi-dbea9bd8c94989c40e6a5d62dfcf986413c823c9-2aa92d550c51ecdd407f0fa6d2d60220"
                }
            ]
        },
        {
            "Category": "M25 Ajaccio",
            "League": "M25 Ajaccio",
            "Team 1 Name": "Matisse Bobichon",
            "Team 2 Name": "Niels Villard",
            "Team 1 Logo": "https://img.bingstream.info/static/common/thumbs/soccer/team_placeholder_45x45.png",
            "Team 2 Logo": "https://img.bingstream.info/static/common/thumbs/soccer/team_placeholder_45x45.png",
            "Match Title": "Matisse Bobichon VS Niels Villard | M25 Ajaccio",
            "Match Poster": "https://static.vecteezy.com/system/resources/previews/016/314/808/original/transparent-live-transparent-live-icon-free-png.png",
            "Match Status": "Live",
            "Start Time": "Live Now",
            "User-Agent": "Mozilla/5.0 (Linux; Android 10; K) AppleWebKit/537.36 (KHTML, like Gecko) Chrome/120.0.0.0 Mobile Safari/537.36",
            "Referer": "https://iframe.rumsport10.live/",
            "Stream URL": [
                {
                    "server_name": "Server 1",
                    "play_url": "https://livecdn-bp-livestream.rumsport10.live/sla/13-6a433fba4e6abdac611334d8/chunks.m3u8?is_vip=false&token=dbea9bd8c94989c40e6a5d62dfcf986413c823c9&x-sign=5cc0f9be1b46be84b01329408a807473&x-time=1782799380"
                },
                {
                    "server_name": "Server 2",
                    "play_url": "https://livecdn-tc-livestream.rumsport10.live/sla/13-6a433fba4e6abdac611334d8/chunks.m3u8?is_vip=false&token=1782885810-Kv4cPTAAP5YTi-dbea9bd8c94989c40e6a5d62dfcf986413c823c9-9bca5a4b1b50ade9326dddc76d392a93"
                }
            ]
        },
        {
            "Category": "NPB Farm Leagues",
            "League": "NPB Farm Leagues",
            "Team 1 Name": "",
            "Team 2 Name": "",
            "Team 1 Logo": "",
            "Team 2 Logo": "",
            "Match Title": "Oisix Niigata VS Chiba Lotte Marines | NPB Farm Leagues",
            "Match Poster": "https://static.vecteezy.com/system/resources/previews/016/314/808/original/transparent-live-transparent-live-icon-free-png.png",
            "Match Status": "Live",
            "Start Time": "Live Now",
            "User-Agent": "Mozilla/5.0 (Linux; Android 10; K) AppleWebKit/537.36 (KHTML, like Gecko) Chrome/120.0.0.0 Mobile Safari/537.36",
            "Referer": "https://iframe.rumsport10.live/",
            "Stream URL": [
                {
                    "server_name": "Server 1",
                    "play_url": "https://livecdn-tc-livestream.rumsport10.live/stream/9/chunks.m3u8?is_vip=false&token=1782885815-Kv4cPTAAP5YTi-dbea9bd8c94989c40e6a5d62dfcf986413c823c9-b36442cbe14bba1db74d5328738c7819"
                },
                {
                    "server_name": "Server 2",
                    "play_url": "https://livecdn-bp-livestream.rumsport7.live/stream/9/chunks.m3u8?is_vip=false&token=dbea9bd8c94989c40e6a5d62dfcf986413c823c9&x-sign=7379145662f2beed73a96794b93cd823&x-time=1782799380"
                }
            ]
        },
        {
            "Category": "W35 Amstelveen",
            "League": "W35 Amstelveen",
            "Team 1 Name": "Carmen Andreea Herea",
            "Team 2 Name": "Rikke De Koning",
            "Team 1 Logo": "https://img.bingstream.info/static/common/thumbs/soccer/team_placeholder_45x45.png",
            "Team 2 Logo": "https://img.bingstream.info/static/common/thumbs/soccer/team_placeholder_45x45.png",
            "Match Title": "Carmen Andreea Herea VS Rikke De Koning | W35 Amstelveen",
            "Match Poster": "https://static.vecteezy.com/system/resources/previews/016/314/808/original/transparent-live-transparent-live-icon-free-png.png",
            "Match Status": "Live",
            "Start Time": "Live Now",
            "User-Agent": "Mozilla/5.0 (Linux; Android 10; K) AppleWebKit/537.36 (KHTML, like Gecko) Chrome/120.0.0.0 Mobile Safari/537.36",
            "Referer": "https://iframe.rumsport10.live/",
            "Stream URL": [
                {
                    "server_name": "Server 1",
                    "play_url": "https://livecdn-bp-livestream.rumsport10.live/sla/13-6a4331bc9a1d202ef66b2d74/chunks.m3u8?is_vip=false&token=dbea9bd8c94989c40e6a5d62dfcf986413c823c9&x-sign=f3e9ffa4e4b59d43eeaa0dad1df1095e&x-time=1782799380"
                },
                {
                    "server_name": "Server 2",
                    "play_url": "https://livecdn-tc-livestream.rumsport10.live/sla/13-6a4331bc9a1d202ef66b2d74/chunks.m3u8?is_vip=false&token=1782885820-Kv4cPTAAP5YTi-dbea9bd8c94989c40e6a5d62dfcf986413c823c9-20927b15ce630cb764569f3f44a827a7"
                }
            ]
        },
        {
            "Category": "W35 Amstelveen",
            "League": "W35 Amstelveen",
            "Team 1 Name": "Jule Niemeier",
            "Team 2 Name": "Emma Kamper",
            "Team 1 Logo": "https://img.bingstream.info/static/common/thumbs/soccer/team_placeholder_45x45.png",
            "Team 2 Logo": "https://img.bingstream.info/static/common/thumbs/soccer/team_placeholder_45x45.png",
            "Match Title": "Jule Niemeier VS Emma Kamper | W35 Amstelveen",
            "Match Poster": "https://static.vecteezy.com/system/resources/previews/016/314/808/original/transparent-live-transparent-live-icon-free-png.png",
            "Match Status": "Live",
            "Start Time": "Live Now",
            "User-Agent": "Mozilla/5.0 (Linux; Android 10; K) AppleWebKit/537.36 (KHTML, like Gecko) Chrome/120.0.0.0 Mobile Safari/537.36",
            "Referer": "https://iframe.rumsport10.live/",
            "Stream URL": [
                {
                    "server_name": "Server 1",
                    "play_url": "https://livecdn-bp-livestream.rumsport10.live/sla/13-6a4331bc55d8b708a7d26208/chunks.m3u8?is_vip=false&token=dbea9bd8c94989c40e6a5d62dfcf986413c823c9&x-sign=22d250705848960ea928008ded50da47&x-time=1782799380"
                },
                {
                    "server_name": "Server 2",
                    "play_url": "https://livecdn-tc-livestream.rumsport10.live/sla/13-6a4331bc55d8b708a7d26208/chunks.m3u8?is_vip=false&token=1782885825-Kv4cPTAAP5YTi-dbea9bd8c94989c40e6a5d62dfcf986413c823c9-f2aacaa076705e7193c487140a412c3d"
                }
            ]
        },
        {
            "Category": "M15 Monastir",
            "League": "M15 Monastir",
            "Team 1 Name": "Karim Mabrouk",
            "Team 2 Name": "Arin Pallegar",
            "Team 1 Logo": "https://img.bingstream.info/static/common/thumbs/soccer/team_placeholder_45x45.png",
            "Team 2 Logo": "https://img.bingstream.info/static/common/thumbs/soccer/team_placeholder_45x45.png",
            "Match Title": "Karim Mabrouk VS Arin Pallegar | M15 Monastir",
            "Match Poster": "https://static.vecteezy.com/system/resources/previews/016/314/808/original/transparent-live-transparent-live-icon-free-png.png",
            "Match Status": "Live",
            "Start Time": "Live Now",
            "User-Agent": "Mozilla/5.0 (Linux; Android 10; K) AppleWebKit/537.36 (KHTML, like Gecko) Chrome/120.0.0.0 Mobile Safari/537.36",
            "Referer": "https://iframe.rumsport10.live/",
            "Stream URL": [
                {
                    "server_name": "Server 1",
                    "play_url": "https://livecdn-bp-livestream.rumsport10.live/sla/13-6a4331bc9a1d202ef66b2d71/chunks.m3u8?is_vip=false&token=dbea9bd8c94989c40e6a5d62dfcf986413c823c9&x-sign=31b3cf963e4b82a28fe366a46b1a777a&x-time=1782799380"
                },
                {
                    "server_name": "Server 2",
                    "play_url": "https://livecdn-tc-livestream.rumsport10.live/sla/13-6a4331bc9a1d202ef66b2d71/chunks.m3u8?is_vip=false&token=1782885830-Kv4cPTAAP5YTi-dbea9bd8c94989c40e6a5d62dfcf986413c823c9-80f7b20c49b3a816d3b724ea660061a6"
                }
            ]
        },
        {
            "Category": "M15 Monastir",
            "League": "M15 Monastir",
            "Team 1 Name": "Billy Blaydes",
            "Team 2 Name": "Gawad El Feky",
            "Team 1 Logo": "https://img.bingstream.info/static/common/thumbs/soccer/team_placeholder_45x45.png",
            "Team 2 Logo": "https://img.bingstream.info/static/common/thumbs/soccer/team_placeholder_45x45.png",
            "Match Title": "Billy Blaydes VS Gawad El Feky | M15 Monastir",
            "Match Poster": "https://static.vecteezy.com/system/resources/previews/016/314/808/original/transparent-live-transparent-live-icon-free-png.png",
            "Match Status": "Live",
            "Start Time": "Live Now",
            "User-Agent": "Mozilla/5.0 (Linux; Android 10; K) AppleWebKit/537.36 (KHTML, like Gecko) Chrome/120.0.0.0 Mobile Safari/537.36",
            "Referer": "https://iframe.rumsport10.live/",
            "Stream URL": [
                {
                    "server_name": "Server 1",
                    "play_url": "https://livecdn-bp-livestream.rumsport10.live/sla/13-6a4331bcd06bfc5094dc9e8a/chunks.m3u8?is_vip=false&token=dbea9bd8c94989c40e6a5d62dfcf986413c823c9&x-sign=2b0b1d905e7f4a8f7d2ab0c14a36ac78&x-time=1782799380"
                },
                {
                    "server_name": "Server 2",
                    "play_url": "https://livecdn-tc-livestream.rumsport10.live/sla/13-6a4331bcd06bfc5094dc9e8a/chunks.m3u8?is_vip=false&token=1782885835-Kv4cPTAAP5YTi-dbea9bd8c94989c40e6a5d62dfcf986413c823c9-023c4dff5e134dc47e5e7e75144face3"
                }
            ]
        },
        {
            "Category": "M15 Kursumlijska Banja",
            "League": "M15 Kursumlijska Banja",
            "Team 1 Name": "Aleksandar Lavrnja",
            "Team 2 Name": "Marko Bekeni",
            "Team 1 Logo": "https://img.bingstream.info/static/common/thumbs/soccer/team_placeholder_45x45.png",
            "Team 2 Logo": "https://img.bingstream.info/static/common/thumbs/soccer/team_placeholder_45x45.png",
            "Match Title": "Aleksandar Lavrnja VS Marko Bekeni | M15 Kursumlijska Banja",
            "Match Poster": "https://static.vecteezy.com/system/resources/previews/016/314/808/original/transparent-live-transparent-live-icon-free-png.png",
            "Match Status": "Live",
            "Start Time": "Live Now",
            "User-Agent": "Mozilla/5.0 (Linux; Android 10; K) AppleWebKit/537.36 (KHTML, like Gecko) Chrome/120.0.0.0 Mobile Safari/537.36",
            "Referer": "https://iframe.rumsport10.live/",
            "Stream URL": [
                {
                    "server_name": "Server 1",
                    "play_url": "https://livecdn-bp-livestream.rumsport10.live/sla/13-6a4331bc30392eaef4a6e206/chunks.m3u8?is_vip=false&token=dbea9bd8c94989c40e6a5d62dfcf986413c823c9&x-sign=0dc3341cd1c83f0bc33f0bbb2c0427d8&x-time=1782799380"
                },
                {
                    "server_name": "Server 2",
                    "play_url": "https://livecdn-tc-livestream.rumsport10.live/sla/13-6a4331bc30392eaef4a6e206/chunks.m3u8?is_vip=false&token=1782885840-Kv4cPTAAP5YTi-dbea9bd8c94989c40e6a5d62dfcf986413c823c9-ffe85c237f967810db828035b1a6ca2b"
                }
            ]
        },
        {
            "Category": "W35 Amstelveen",
            "League": "W35 Amstelveen",
            "Team 1 Name": "Monika Wojcik",
            "Team 2 Name": "Polina Kuharenko",
            "Team 1 Logo": "https://img.bingstream.info/static/common/thumbs/soccer/team_placeholder_45x45.png",
            "Team 2 Logo": "https://img.bingstream.info/static/common/thumbs/soccer/team_placeholder_45x45.png",
            "Match Title": "Monika Wojcik VS Polina Kuharenko | W35 Amstelveen",
            "Match Poster": "https://static.vecteezy.com/system/resources/previews/016/314/808/original/transparent-live-transparent-live-icon-free-png.png",
            "Match Status": "Live",
            "Start Time": "Live Now",
            "User-Agent": "Mozilla/5.0 (Linux; Android 10; K) AppleWebKit/537.36 (KHTML, like Gecko) Chrome/120.0.0.0 Mobile Safari/537.36",
            "Referer": "https://iframe.rumsport10.live/",
            "Stream URL": [
                {
                    "server_name": "Server 1",
                    "play_url": "https://livecdn-bp-livestream.rumsport10.live/sla/13-6a4331bc00567544417eadf1/chunks.m3u8?is_vip=false&token=dbea9bd8c94989c40e6a5d62dfcf986413c823c9&x-sign=4abf66929c65da44d37020c786970628&x-time=1782799440"
                },
                {
                    "server_name": "Server 2",
                    "play_url": "https://livecdn-tc-livestream.rumsport10.live/sla/13-6a4331bc00567544417eadf1/chunks.m3u8?is_vip=false&token=1782885844-Kv4cPTAAP5YTi-dbea9bd8c94989c40e6a5d62dfcf986413c823c9-9bd21bb09e3a95587d5579691883ad81"
                }
            ]
        },
        {
            "Category": "M15 Kursumlijska Banja",
            "League": "M15 Kursumlijska Banja",
            "Team 1 Name": "George Lazarov",
            "Team 2 Name": "Dusan Obradovic",
            "Team 1 Logo": "https://img.bingstream.info/static/common/thumbs/soccer/team_placeholder_45x45.png",
            "Team 2 Logo": "https://img.bingstream.info/static/common/thumbs/soccer/team_placeholder_45x45.png",
            "Match Title": "George Lazarov VS Dusan Obradovic | M15 Kursumlijska Banja",
            "Match Poster": "https://static.vecteezy.com/system/resources/previews/016/314/808/original/transparent-live-transparent-live-icon-free-png.png",
            "Match Status": "Live",
            "Start Time": "Live Now",
            "User-Agent": "Mozilla/5.0 (Linux; Android 10; K) AppleWebKit/537.36 (KHTML, like Gecko) Chrome/120.0.0.0 Mobile Safari/537.36",
            "Referer": "https://iframe.rumsport10.live/",
            "Stream URL": [
                {
                    "server_name": "Server 1",
                    "play_url": "https://livecdn-bp-livestream.rumsport10.live/sla/13-6a4331bcf65afa224ef23910/chunks.m3u8?is_vip=false&token=dbea9bd8c94989c40e6a5d62dfcf986413c823c9&x-sign=c1a1047e4ef829575eb258368cab8430&x-time=1782799440"
                },
                {
                    "server_name": "Server 2",
                    "play_url": "https://livecdn-tc-livestream.rumsport10.live/sla/13-6a4331bcf65afa224ef23910/chunks.m3u8?is_vip=false&token=1782885849-Kv4cPTAAP5YTi-dbea9bd8c94989c40e6a5d62dfcf986413c823c9-4e1b41996a878798d3ac88519ef6fbc0"
                }
            ]
        },
        {
            "Category": "W35 Amstelveen",
            "League": "W35 Amstelveen",
            "Team 1 Name": "Sarah Van Emst",
            "Team 2 Name": "Lavinia Tanasie",
            "Team 1 Logo": "https://img.bingstream.info/static/common/thumbs/soccer/team_placeholder_45x45.png",
            "Team 2 Logo": "https://img.bingstream.info/static/common/thumbs/soccer/team_placeholder_45x45.png",
            "Match Title": "Sarah Van Emst VS Lavinia Tanasie | W35 Amstelveen",
            "Match Poster": "https://static.vecteezy.com/system/resources/previews/016/314/808/original/transparent-live-transparent-live-icon-free-png.png",
            "Match Status": "Live",
            "Start Time": "Live Now",
            "User-Agent": "Mozilla/5.0 (Linux; Android 10; K) AppleWebKit/537.36 (KHTML, like Gecko) Chrome/120.0.0.0 Mobile Safari/537.36",
            "Referer": "https://iframe.rumsport10.live/",
            "Stream URL": [
                {
                    "server_name": "Server 1",
                    "play_url": "https://livecdn-bp-livestream.rumsport10.live/sla/13-6a4331bc1ceff89491a7b1ac/chunks.m3u8?is_vip=false&token=dbea9bd8c94989c40e6a5d62dfcf986413c823c9&x-sign=2274c8091c7144a8663125be7ae68296&x-time=1782799440"
                },
                {
                    "server_name": "Server 2",
                    "play_url": "https://livecdn-tc-livestream.rumsport10.live/sla/13-6a4331bc1ceff89491a7b1ac/chunks.m3u8?is_vip=false&token=1782885854-Kv4cPTAAP5YTi-dbea9bd8c94989c40e6a5d62dfcf986413c823c9-6da34cb9fea6d1be721cd6516cf5a0f6"
                }
            ]
        },
        {
            "Category": "M15 Amstelveen",
            "League": "M15 Amstelveen",
            "Team 1 Name": "Louis Tessa",
            "Team 2 Name": "Pranav Karthik",
            "Team 1 Logo": "https://img.bingstream.info/static/common/thumbs/soccer/team_placeholder_45x45.png",
            "Team 2 Logo": "https://img.bingstream.info/static/common/thumbs/soccer/team_placeholder_45x45.png",
            "Match Title": "Louis Tessa VS Pranav Karthik | M15 Amstelveen",
            "Match Poster": "https://static.vecteezy.com/system/resources/previews/016/314/808/original/transparent-live-transparent-live-icon-free-png.png",
            "Match Status": "Live",
            "Start Time": "Live Now",
            "User-Agent": "Mozilla/5.0 (Linux; Android 10; K) AppleWebKit/537.36 (KHTML, like Gecko) Chrome/120.0.0.0 Mobile Safari/537.36",
            "Referer": "https://iframe.rumsport10.live/",
            "Stream URL": [
                {
                    "server_name": "Server 1",
                    "play_url": "https://livecdn-bp-livestream.rumsport10.live/sla/13-6a4331bc1ceff89491a7b1ad/chunks.m3u8?is_vip=false&token=dbea9bd8c94989c40e6a5d62dfcf986413c823c9&x-sign=cb511863e7a4854e7e3648acab0e16eb&x-time=1782799440"
                },
                {
                    "server_name": "Server 2",
                    "play_url": "https://livecdn-tc-livestream.rumsport10.live/sla/13-6a4331bc1ceff89491a7b1ad/chunks.m3u8?is_vip=false&token=1782885859-Kv4cPTAAP5YTi-dbea9bd8c94989c40e6a5d62dfcf986413c823c9-d2c8964efd42ed1506ed76fac6b9cb28"
                }
            ]
        },
        {
            "Category": "W35 Amstelveen",
            "League": "W35 Amstelveen",
            "Team 1 Name": "Nellie Taraba Wallberg",
            "Team 2 Name": "Seda Baslilar",
            "Team 1 Logo": "https://img.bingstream.info/static/common/thumbs/soccer/team_placeholder_45x45.png",
            "Team 2 Logo": "https://img.bingstream.info/static/common/thumbs/soccer/team_placeholder_45x45.png",
            "Match Title": "Nellie Taraba Wallberg VS Seda Baslilar | W35 Amstelveen",
            "Match Poster": "https://static.vecteezy.com/system/resources/previews/016/314/808/original/transparent-live-transparent-live-icon-free-png.png",
            "Match Status": "Live",
            "Start Time": "Live Now",
            "User-Agent": "Mozilla/5.0 (Linux; Android 10; K) AppleWebKit/537.36 (KHTML, like Gecko) Chrome/120.0.0.0 Mobile Safari/537.36",
            "Referer": "https://iframe.rumsport10.live/",
            "Stream URL": [
                {
                    "server_name": "Server 1",
                    "play_url": "https://livecdn-bp-livestream.rumsport10.live/sla/13-6a4331bcebc5c3ef2c96f7b1/chunks.m3u8?is_vip=false&token=dbea9bd8c94989c40e6a5d62dfcf986413c823c9&x-sign=a341902ce50814a98efe2259469ee7d9&x-time=1782799440"
                },
                {
                    "server_name": "Server 2",
                    "play_url": "https://livecdn-tc-livestream.rumsport10.live/sla/13-6a4331bcebc5c3ef2c96f7b1/chunks.m3u8?is_vip=false&token=1782885864-Kv4cPTAAP5YTi-dbea9bd8c94989c40e6a5d62dfcf986413c823c9-dbf81d2f32ab3350a7f62de299657b2b"
                }
            ]
        },
        {
            "Category": "W35 Amstelveen",
            "League": "W35 Amstelveen",
            "Team 1 Name": "Linea Bajraliu",
            "Team 2 Name": "Jade Groen",
            "Team 1 Logo": "https://img.bingstream.info/static/common/thumbs/soccer/team_placeholder_45x45.png",
            "Team 2 Logo": "https://img.bingstream.info/static/common/thumbs/soccer/team_placeholder_45x45.png",
            "Match Title": "Linea Bajraliu VS Jade Groen | W35 Amstelveen",
            "Match Poster": "https://static.vecteezy.com/system/resources/previews/016/314/808/original/transparent-live-transparent-live-icon-free-png.png",
            "Match Status": "Live",
            "Start Time": "Live Now",
            "User-Agent": "Mozilla/5.0 (Linux; Android 10; K) AppleWebKit/537.36 (KHTML, like Gecko) Chrome/120.0.0.0 Mobile Safari/537.36",
            "Referer": "https://iframe.rumsport10.live/",
            "Stream URL": [
                {
                    "server_name": "Server 1",
                    "play_url": "https://livecdn-bp-livestream.rumsport10.live/sla/13-6a4331bc55d8b708a7d26209/chunks.m3u8?is_vip=false&token=dbea9bd8c94989c40e6a5d62dfcf986413c823c9&x-sign=78759ccc379bb04c0daa78f34fc9c74f&x-time=1782799440"
                },
                {
                    "server_name": "Server 2",
                    "play_url": "https://livecdn-tc-livestream.rumsport10.live/sla/13-6a4331bc55d8b708a7d26209/chunks.m3u8?is_vip=false&token=1782885869-Kv4cPTAAP5YTi-dbea9bd8c94989c40e6a5d62dfcf986413c823c9-9876ea78525c5202b40da35149a9ef56"
                }
            ]
        },
        {
            "Category": "W35 Amstelveen",
            "League": "W35 Amstelveen",
            "Team 1 Name": "Sara Cakarevic",
            "Team 2 Name": "Amelie Brooks",
            "Team 1 Logo": "https://img.bingstream.info/static/common/thumbs/soccer/team_placeholder_45x45.png",
            "Team 2 Logo": "https://img.bingstream.info/static/common/thumbs/soccer/team_placeholder_45x45.png",
            "Match Title": "Sara Cakarevic VS Amelie Brooks | W35 Amstelveen",
            "Match Poster": "https://static.vecteezy.com/system/resources/previews/016/314/808/original/transparent-live-transparent-live-icon-free-png.png",
            "Match Status": "Live",
            "Start Time": "Live Now",
            "User-Agent": "Mozilla/5.0 (Linux; Android 10; K) AppleWebKit/537.36 (KHTML, like Gecko) Chrome/120.0.0.0 Mobile Safari/537.36",
            "Referer": "https://iframe.rumsport10.live/",
            "Stream URL": [
                {
                    "server_name": "Server 1",
                    "play_url": "https://livecdn-bp-livestream.rumsport10.live/sla/13-6a4331bc55d8b708a7d2620b/chunks.m3u8?is_vip=false&token=dbea9bd8c94989c40e6a5d62dfcf986413c823c9&x-sign=d5611ed2741ae3d84e316bd7889f94a8&x-time=1782799440"
                },
                {
                    "server_name": "Server 2",
                    "play_url": "https://livecdn-tc-livestream.rumsport10.live/sla/13-6a4331bc55d8b708a7d2620b/chunks.m3u8?is_vip=false&token=1782885874-Kv4cPTAAP5YTi-dbea9bd8c94989c40e6a5d62dfcf986413c823c9-d5df45d8bee0a26f1de3681d70fa3045"
                }
            ]
        },
        {
            "Category": "M25 Figueira da Foz",
            "League": "M25 Figueira da Foz",
            "Team 1 Name": "Matthew Summers",
            "Team 2 Name": "Mario Gonzalez Fernandez",
            "Team 1 Logo": "https://img.bingstream.info/static/common/thumbs/soccer/team_placeholder_45x45.png",
            "Team 2 Logo": "https://img.bingstream.info/static/common/thumbs/soccer/team_placeholder_45x45.png",
            "Match Title": "Matthew Summers VS Mario Gonzalez Fernandez | M25 Figueira da Foz",
            "Match Poster": "https://static.vecteezy.com/system/resources/previews/016/314/808/original/transparent-live-transparent-live-icon-free-png.png",
            "Match Status": "Live",
            "Start Time": "Live Now",
            "User-Agent": "Mozilla/5.0 (Linux; Android 10; K) AppleWebKit/537.36 (KHTML, like Gecko) Chrome/120.0.0.0 Mobile Safari/537.36",
            "Referer": "https://iframe.rumsport10.live/",
            "Stream URL": [
                {
                    "server_name": "Server 1",
                    "play_url": "https://livecdn-bp-livestream.rumsport10.live/sla/13-6a433fba4b4d858b85c3d4f5/chunks.m3u8?is_vip=false&token=dbea9bd8c94989c40e6a5d62dfcf986413c823c9&x-sign=a1092ce8ccb1f3b78a002bdd4cbbbbb0&x-time=1782799440"
                },
                {
                    "server_name": "Server 2",
                    "play_url": "https://livecdn-tc-livestream.rumsport10.live/sla/13-6a433fba4b4d858b85c3d4f5/chunks.m3u8?is_vip=false&token=1782885879-Kv4cPTAAP5YTi-dbea9bd8c94989c40e6a5d62dfcf986413c823c9-2451c955208335c667a923aa8ac4e9f9"
                }
            ]
        },
        {
            "Category": "M15 Hillcrest MD",
            "League": "M15 Hillcrest MD",
            "Team 1 Name": "Host/Jefferson",
            "Team 2 Name": "Doig/Jestin",
            "Team 1 Logo": "https://img.bingstream.info/static/common/thumbs/soccer/team_placeholder_45x45.png",
            "Team 2 Logo": "https://img.bingstream.info/static/common/thumbs/soccer/team_placeholder_45x45.png",
            "Match Title": "Host/Jefferson VS Doig/Jestin | M15 Hillcrest MD",
            "Match Poster": "https://static.vecteezy.com/system/resources/previews/016/314/808/original/transparent-live-transparent-live-icon-free-png.png",
            "Match Status": "Live",
            "Start Time": "Live Now",
            "User-Agent": "Mozilla/5.0 (Linux; Android 10; K) AppleWebKit/537.36 (KHTML, like Gecko) Chrome/120.0.0.0 Mobile Safari/537.36",
            "Referer": "https://iframe.rumsport10.live/",
            "Stream URL": [
                {
                    "server_name": "Server 1",
                    "play_url": "https://livecdn-bp-livestream.rumsport10.live/sla/13-6a4331bc55d8b708a7d2620c/chunks.m3u8?is_vip=false&token=dbea9bd8c94989c40e6a5d62dfcf986413c823c9&x-sign=4eac35bf8950d5f608600fe4696e6a26&x-time=1782799440"
                },
                {
                    "server_name": "Server 2",
                    "play_url": "https://livecdn-tc-livestream.rumsport10.live/sla/13-6a4331bc55d8b708a7d2620c/chunks.m3u8?is_vip=false&token=1782885883-Kv4cPTAAP5YTi-dbea9bd8c94989c40e6a5d62dfcf986413c823c9-16be4e1be598c2debecd5fe1e032cc86"
                }
            ]
        },
        {
            "Category": "W35 Aix-les-Bains",
            "League": "W35 Aix-les-Bains",
            "Team 1 Name": "Amy Stevens",
            "Team 2 Name": "Oceane Dodin",
            "Team 1 Logo": "https://img.bingstream.info/static/common/thumbs/soccer/team_placeholder_45x45.png",
            "Team 2 Logo": "https://img.bingstream.info/static/common/thumbs/soccer/team_placeholder_45x45.png",
            "Match Title": "Amy Stevens VS Oceane Dodin | W35 Aix-les-Bains",
            "Match Poster": "https://static.vecteezy.com/system/resources/previews/016/314/808/original/transparent-live-transparent-live-icon-free-png.png",
            "Match Status": "Live",
            "Start Time": "Live Now",
            "User-Agent": "Mozilla/5.0 (Linux; Android 10; K) AppleWebKit/537.36 (KHTML, like Gecko) Chrome/120.0.0.0 Mobile Safari/537.36",
            "Referer": "https://iframe.rumsport10.live/",
            "Stream URL": [
                {
                    "server_name": "Server 1",
                    "play_url": "https://livecdn-bp-livestream.rumsport10.live/sla/13-6a4331bc9a1d202ef66b2d76/chunks.m3u8?is_vip=false&token=dbea9bd8c94989c40e6a5d62dfcf986413c823c9&x-sign=d4c7fd0095326582971c279bedd5cac3&x-time=1782799440"
                },
                {
                    "server_name": "Server 2",
                    "play_url": "https://livecdn-tc-livestream.rumsport10.live/sla/13-6a4331bc9a1d202ef66b2d76/chunks.m3u8?is_vip=false&token=1782885888-Kv4cPTAAP5YTi-dbea9bd8c94989c40e6a5d62dfcf986413c823c9-00103b704c397c0ce826685755d200fb"
                }
            ]
        },
        {
            "Category": "M15 Hillcrest MD",
            "League": "M15 Hillcrest MD",
            "Team 1 Name": "Caripi/Wyk",
            "Team 2 Name": "Van Der Merwe/Voelzke",
            "Team 1 Logo": "https://img.bingstream.info/static/common/thumbs/soccer/team_placeholder_45x45.png",
            "Team 2 Logo": "https://img.bingstream.info/static/common/thumbs/soccer/team_placeholder_45x45.png",
            "Match Title": "Caripi/Wyk VS Van Der Merwe/Voelzke | M15 Hillcrest MD",
            "Match Poster": "https://static.vecteezy.com/system/resources/previews/016/314/808/original/transparent-live-transparent-live-icon-free-png.png",
            "Match Status": "Live",
            "Start Time": "Live Now",
            "User-Agent": "Mozilla/5.0 (Linux; Android 10; K) AppleWebKit/537.36 (KHTML, like Gecko) Chrome/120.0.0.0 Mobile Safari/537.36",
            "Referer": "https://iframe.rumsport10.live/",
            "Stream URL": [
                {
                    "server_name": "Server 1",
                    "play_url": "https://livecdn-bp-livestream.rumsport10.live/sla/13-6a4331bcd06bfc5094dc9e8c/chunks.m3u8?is_vip=false&token=dbea9bd8c94989c40e6a5d62dfcf986413c823c9&x-sign=944eda0b3bd581f85e02ab74048cab0b&x-time=1782799440"
                },
                {
                    "server_name": "Server 2",
                    "play_url": "https://livecdn-tc-livestream.rumsport10.live/sla/13-6a4331bcd06bfc5094dc9e8c/chunks.m3u8?is_vip=false&token=1782885893-Kv4cPTAAP5YTi-dbea9bd8c94989c40e6a5d62dfcf986413c823c9-7983404bfacdc3f8c63885d41fe0e683"
                }
            ]
        },
        {
            "Category": "M15 Amstelveen",
            "League": "M15 Amstelveen",
            "Team 1 Name": "Lars Wagenaar",
            "Team 2 Name": "Abel Forger",
            "Team 1 Logo": "https://img.bingstream.info/static/common/thumbs/soccer/team_placeholder_45x45.png",
            "Team 2 Logo": "https://img.bingstream.info/static/common/thumbs/soccer/team_placeholder_45x45.png",
            "Match Title": "Lars Wagenaar VS Abel Forger | M15 Amstelveen",
            "Match Poster": "https://static.vecteezy.com/system/resources/previews/016/314/808/original/transparent-live-transparent-live-icon-free-png.png",
            "Match Status": "Live",
            "Start Time": "Live Now",
            "User-Agent": "Mozilla/5.0 (Linux; Android 10; K) AppleWebKit/537.36 (KHTML, like Gecko) Chrome/120.0.0.0 Mobile Safari/537.36",
            "Referer": "https://iframe.rumsport10.live/",
            "Stream URL": [
                {
                    "server_name": "Server 1",
                    "play_url": "https://livecdn-bp-livestream.rumsport10.live/sla/13-6a42b2fe9a1d202ef664c82c/chunks.m3u8?is_vip=false&token=dbea9bd8c94989c40e6a5d62dfcf986413c823c9&x-sign=45765a0e5dc409a5eda7814cfc99a96e&x-time=1782799440"
                },
                {
                    "server_name": "Server 2",
                    "play_url": "https://livecdn-tc-livestream.rumsport10.live/sla/13-6a42b2fe9a1d202ef664c82c/chunks.m3u8?is_vip=false&token=1782885898-Kv4cPTAAP5YTi-dbea9bd8c94989c40e6a5d62dfcf986413c823c9-5f4d9171bc6f56031987ef114585c822"
                }
            ]
        },
        {
            "Category": "W50 Stuttgart-Vaihingen",
            "League": "W50 Stuttgart-Vaihingen",
            "Team 1 Name": "Denislava Glushkova",
            "Team 2 Name": "Luisa Meyer Auf Der Heide",
            "Team 1 Logo": "https://img.bingstream.info/static/common/thumbs/soccer/team_placeholder_45x45.png",
            "Team 2 Logo": "https://img.bingstream.info/static/common/thumbs/soccer/team_placeholder_45x45.png",
            "Match Title": "Denislava Glushkova VS Luisa Meyer Auf Der Heide | W50 Stuttgart-Vaihingen",
            "Match Poster": "https://static.vecteezy.com/system/resources/previews/016/314/808/original/transparent-live-transparent-live-icon-free-png.png",
            "Match Status": "Live",
            "Start Time": "Live Now",
            "User-Agent": "Mozilla/5.0 (Linux; Android 10; K) AppleWebKit/537.36 (KHTML, like Gecko) Chrome/120.0.0.0 Mobile Safari/537.36",
            "Referer": "https://iframe.rumsport10.live/",
            "Stream URL": [
                {
                    "server_name": "Server 1",
                    "play_url": "https://livecdn-bp-livestream.rumsport10.live/sla/13-6a433fbabb875b4ddf463fad/chunks.m3u8?is_vip=false&token=dbea9bd8c94989c40e6a5d62dfcf986413c823c9&x-sign=f1fb2cb3e6b5ad34cc802f608bb6e52a&x-time=1782799500"
                },
                {
                    "server_name": "Server 2",
                    "play_url": "https://livecdn-tc-livestream.rumsport10.live/sla/13-6a433fbabb875b4ddf463fad/chunks.m3u8?is_vip=false&token=1782885903-Kv4cPTAAP5YTi-dbea9bd8c94989c40e6a5d62dfcf986413c823c9-140547b36540dcad59ddc30a26f1d108"
                }
            ]
        },
        {
            "Category": "W50 Stuttgart-Vaihingen",
            "League": "W50 Stuttgart-Vaihingen",
            "Team 1 Name": "Martina Okalova",
            "Team 2 Name": "Petra Sedlackova",
            "Team 1 Logo": "https://img.bingstream.info/static/common/thumbs/soccer/team_placeholder_45x45.png",
            "Team 2 Logo": "https://img.bingstream.info/static/common/thumbs/soccer/team_placeholder_45x45.png",
            "Match Title": "Martina Okalova VS Petra Sedlackova | W50 Stuttgart-Vaihingen",
            "Match Poster": "https://static.vecteezy.com/system/resources/previews/016/314/808/original/transparent-live-transparent-live-icon-free-png.png",
            "Match Status": "Live",
            "Start Time": "Live Now",
            "User-Agent": "Mozilla/5.0 (Linux; Android 10; K) AppleWebKit/537.36 (KHTML, like Gecko) Chrome/120.0.0.0 Mobile Safari/537.36",
            "Referer": "https://iframe.rumsport10.live/",
            "Stream URL": [
                {
                    "server_name": "Server 1",
                    "play_url": "https://livecdn-bp-livestream.rumsport10.live/sla/13-6a433fbabb875b4ddf463fae/chunks.m3u8?is_vip=false&token=dbea9bd8c94989c40e6a5d62dfcf986413c823c9&x-sign=cf0607b977ebc9c1a9edeefb8697773a&x-time=1782799500"
                },
                {
                    "server_name": "Server 2",
                    "play_url": "https://livecdn-tc-livestream.rumsport10.live/sla/13-6a433fbabb875b4ddf463fae/chunks.m3u8?is_vip=false&token=1782885908-Kv4cPTAAP5YTi-dbea9bd8c94989c40e6a5d62dfcf986413c823c9-49605df84321062faaa8b88960966037"
                }
            ]
        },
        {
            "Category": "W50 Stuttgart-Vaihingen",
            "League": "W50 Stuttgart-Vaihingen",
            "Team 1 Name": "Ipek Oz",
            "Team 2 Name": "Ann Akasha Ceuca",
            "Team 1 Logo": "https://img.bingstream.info/static/common/thumbs/soccer/team_placeholder_45x45.png",
            "Team 2 Logo": "https://img.bingstream.info/static/common/thumbs/soccer/team_placeholder_45x45.png",
            "Match Title": "Ipek Oz VS Ann Akasha Ceuca | W50 Stuttgart-Vaihingen",
            "Match Poster": "https://static.vecteezy.com/system/resources/previews/016/314/808/original/transparent-live-transparent-live-icon-free-png.png",
            "Match Status": "Live",
            "Start Time": "Live Now",
            "User-Agent": "Mozilla/5.0 (Linux; Android 10; K) AppleWebKit/537.36 (KHTML, like Gecko) Chrome/120.0.0.0 Mobile Safari/537.36",
            "Referer": "https://iframe.rumsport10.live/",
            "Stream URL": [
                {
                    "server_name": "Server 1",
                    "play_url": "https://livecdn-bp-livestream.rumsport10.live/sla/13-6a433fba8cf75300576e9328/chunks.m3u8?is_vip=false&token=dbea9bd8c94989c40e6a5d62dfcf986413c823c9&x-sign=d3d0a7920d35f2c07da51b85e15f1789&x-time=1782799500"
                },
                {
                    "server_name": "Server 2",
                    "play_url": "https://livecdn-tc-livestream.rumsport10.live/sla/13-6a433fba8cf75300576e9328/chunks.m3u8?is_vip=false&token=1782885913-Kv4cPTAAP5YTi-dbea9bd8c94989c40e6a5d62dfcf986413c823c9-cc0152382b391bacd67d88aa0ee1f740"
                }
            ]
        },
        {
            "Category": "W50 Stuttgart-Vaihingen",
            "League": "W50 Stuttgart-Vaihingen",
            "Team 1 Name": "Andreea Prisacariu",
            "Team 2 Name": "Lorena Schaedel",
            "Team 1 Logo": "https://img.bingstream.info/static/common/thumbs/soccer/team_placeholder_45x45.png",
            "Team 2 Logo": "https://img.bingstream.info/static/common/thumbs/soccer/team_placeholder_45x45.png",
            "Match Title": "Andreea Prisacariu VS Lorena Schaedel | W50 Stuttgart-Vaihingen",
            "Match Poster": "https://static.vecteezy.com/system/resources/previews/016/314/808/original/transparent-live-transparent-live-icon-free-png.png",
            "Match Status": "Live",
            "Start Time": "Live Now",
            "User-Agent": "Mozilla/5.0 (Linux; Android 10; K) AppleWebKit/537.36 (KHTML, like Gecko) Chrome/120.0.0.0 Mobile Safari/537.36",
            "Referer": "https://iframe.rumsport10.live/",
            "Stream URL": [
                {
                    "server_name": "Server 1",
                    "play_url": "https://livecdn-bp-livestream.rumsport10.live/sla/13-6a433fbaa536306159af4f59/chunks.m3u8?is_vip=false&token=dbea9bd8c94989c40e6a5d62dfcf986413c823c9&x-sign=14ef8f7cbffcb67a71c8e2c05768efed&x-time=1782799500"
                },
                {
                    "server_name": "Server 2",
                    "play_url": "https://livecdn-tc-livestream.rumsport10.live/sla/13-6a433fbaa536306159af4f59/chunks.m3u8?is_vip=false&token=1782885918-Kv4cPTAAP5YTi-dbea9bd8c94989c40e6a5d62dfcf986413c823c9-b6102bcf4f1fdd81ba945e16f7e4135f"
                }
            ]
        },
        {
            "Category": "M25 Figueira da Foz",
            "League": "M25 Figueira da Foz",
            "Team 1 Name": "Lui Maxted",
            "Team 2 Name": "Nikola Djukic Valera",
            "Team 1 Logo": "https://img.bingstream.info/static/common/thumbs/soccer/team_placeholder_45x45.png",
            "Team 2 Logo": "https://img.bingstream.info/static/common/thumbs/soccer/team_placeholder_45x45.png",
            "Match Title": "Lui Maxted VS Nikola Djukic Valera | M25 Figueira da Foz",
            "Match Poster": "https://static.vecteezy.com/system/resources/previews/016/314/808/original/transparent-live-transparent-live-icon-free-png.png",
            "Match Status": "Live",
            "Start Time": "Live Now",
            "User-Agent": "Mozilla/5.0 (Linux; Android 10; K) AppleWebKit/537.36 (KHTML, like Gecko) Chrome/120.0.0.0 Mobile Safari/537.36",
            "Referer": "https://iframe.rumsport10.live/",
            "Stream URL": [
                {
                    "server_name": "Server 1",
                    "play_url": "https://livecdn-bp-livestream.rumsport10.live/sla/13-6a433fba945e9dbcc7a2776c/chunks.m3u8?is_vip=false&token=dbea9bd8c94989c40e6a5d62dfcf986413c823c9&x-sign=46c2383ec2256e9649bc6b377745434f&x-time=1782799500"
                },
                {
                    "server_name": "Server 2",
                    "play_url": "https://livecdn-tc-livestream.rumsport10.live/sla/13-6a433fba945e9dbcc7a2776c/chunks.m3u8?is_vip=false&token=1782885922-Kv4cPTAAP5YTi-dbea9bd8c94989c40e6a5d62dfcf986413c823c9-ba2c079d58f16997161a7449d20a3477"
                }
            ]
        },
        {
            "Category": "M25 Figueira da Foz",
            "League": "M25 Figueira da Foz",
            "Team 1 Name": "Joao Dinis Silva",
            "Team 2 Name": "Dominique Rolland",
            "Team 1 Logo": "https://img.bingstream.info/static/common/thumbs/soccer/team_placeholder_45x45.png",
            "Team 2 Logo": "https://img.bingstream.info/static/common/thumbs/soccer/team_placeholder_45x45.png",
            "Match Title": "Joao Dinis Silva VS Dominique Rolland | M25 Figueira da Foz",
            "Match Poster": "https://static.vecteezy.com/system/resources/previews/016/314/808/original/transparent-live-transparent-live-icon-free-png.png",
            "Match Status": "Live",
            "Start Time": "Live Now",
            "User-Agent": "Mozilla/5.0 (Linux; Android 10; K) AppleWebKit/537.36 (KHTML, like Gecko) Chrome/120.0.0.0 Mobile Safari/537.36",
            "Referer": "https://iframe.rumsport10.live/",
            "Stream URL": [
                {
                    "server_name": "Server 1",
                    "play_url": "https://livecdn-bp-livestream.rumsport10.live/sla/13-6a433fbad8b0af885e3cc01d/chunks.m3u8?is_vip=false&token=dbea9bd8c94989c40e6a5d62dfcf986413c823c9&x-sign=6a48323db7bfe66c9b5bda94ded94175&x-time=1782799500"
                },
                {
                    "server_name": "Server 2",
                    "play_url": "https://livecdn-tc-livestream.rumsport10.live/sla/13-6a433fbad8b0af885e3cc01d/chunks.m3u8?is_vip=false&token=1782885927-Kv4cPTAAP5YTi-dbea9bd8c94989c40e6a5d62dfcf986413c823c9-abe0f3872ab9cf9d517787680e75558a"
                }
            ]
        },
        {
            "Category": "W50 Stuttgart-Vaihingen WD",
            "League": "W50 Stuttgart-Vaihingen WD",
            "Team 1 Name": "Labrana/Pereira",
            "Team 2 Name": "Gavrila/Prisacariu",
            "Team 1 Logo": "https://img.bingstream.info/static/common/thumbs/soccer/team_placeholder_45x45.png",
            "Team 2 Logo": "https://img.bingstream.info/static/common/thumbs/soccer/team_placeholder_45x45.png",
            "Match Title": "Labrana/Pereira VS Gavrila/Prisacariu | W50 Stuttgart-Vaihingen WD",
            "Match Poster": "https://static.vecteezy.com/system/resources/previews/016/314/808/original/transparent-live-transparent-live-icon-free-png.png",
            "Match Status": "Live",
            "Start Time": "Live Now",
            "User-Agent": "Mozilla/5.0 (Linux; Android 10; K) AppleWebKit/537.36 (KHTML, like Gecko) Chrome/120.0.0.0 Mobile Safari/537.36",
            "Referer": "https://iframe.rumsport10.live/",
            "Stream URL": [
                {
                    "server_name": "Server 1",
                    "play_url": "https://livecdn-bp-livestream.rumsport10.live/sla/13-6a434dfbd06bfc5094ddeffb/chunks.m3u8?is_vip=false&token=dbea9bd8c94989c40e6a5d62dfcf986413c823c9&x-sign=293e2f1a345fe7b493991e692838500d&x-time=1782799500"
                },
                {
                    "server_name": "Server 2",
                    "play_url": "https://livecdn-tc-livestream.rumsport10.live/sla/13-6a434dfbd06bfc5094ddeffb/chunks.m3u8?is_vip=false&token=1782885932-Kv4cPTAAP5YTi-dbea9bd8c94989c40e6a5d62dfcf986413c823c9-346b5d8c19ee9c74a998cd6d9c0a22a1"
                }
            ]
        },
        {
            "Category": "World Cup",
            "League": "World Cup",
            "Team 1 Name": "France",
            "Team 2 Name": "Sweden",
            "Team 1 Logo": "https://static-live.linewgen.xyz/live/bing/img/rapid/teams/2.png",
            "Team 2 Logo": "https://static-live.linewgen.xyz/live/bing/img/rapid/teams/5.png",
            "Match Title": "France VS Sweden | World Cup",
            "Match Poster": "https://raw.githubusercontent.com/srhady/axsports/main/bing_posters/France_VS_Sweden_World_Cup.jpg",
            "Match Status": "Upcoming",
            "Start Time": "3:00 AM 01-07-2026",
            "User-Agent": "Mozilla/5.0 (Linux; Android 10; K) AppleWebKit/537.36 (KHTML, like Gecko) Chrome/120.0.0.0 Mobile Safari/537.36",
            "Referer": "https://iframe.rumsport10.live/",
            "Stream URL": []
        },
        {
            "Category": "World Cup",
            "League": "World Cup",
            "Team 1 Name": "England",
            "Team 2 Name": "Congo DR",
            "Team 1 Logo": "https://static-live.linewgen.xyz/live/bing/img/rapid/teams/10.png",
            "Team 2 Logo": "https://static-live.linewgen.xyz/live/bing/img/rapid/teams/1508.png",
            "Match Title": "England VS Congo DR | World Cup",
            "Match Poster": "https://raw.githubusercontent.com/srhady/axsports/main/bing_posters/England_VS_Congo_DR_World_Cup.jpg",
            "Match Status": "Upcoming",
            "Start Time": "10:00 PM 01-07-2026",
            "User-Agent": "Mozilla/5.0 (Linux; Android 10; K) AppleWebKit/537.36 (KHTML, like Gecko) Chrome/120.0.0.0 Mobile Safari/537.36",
            "Referer": "https://iframe.rumsport10.live/",
            "Stream URL": []
        },
        {
            "Category": "World Cup",
            "League": "World Cup",
            "Team 1 Name": "Belgium",
            "Team 2 Name": "Senegal",
            "Team 1 Logo": "https://static-live.linewgen.xyz/live/bing/img/rapid/teams/1.png",
            "Team 2 Logo": "https://static-live.linewgen.xyz/live/bing/img/rapid/teams/13.png",
            "Match Title": "Belgium VS Senegal | World Cup",
            "Match Poster": "https://raw.githubusercontent.com/srhady/axsports/main/bing_posters/Belgium_VS_Senegal_World_Cup.jpg",
            "Match Status": "Upcoming",
            "Start Time": "2:00 AM 02-07-2026",
            "User-Agent": "Mozilla/5.0 (Linux; Android 10; K) AppleWebKit/537.36 (KHTML, like Gecko) Chrome/120.0.0.0 Mobile Safari/537.36",
            "Referer": "https://iframe.rumsport10.live/",
            "Stream URL": []
        },
        {
            "Category": "World Cup",
            "League": "World Cup",
            "Team 1 Name": "Spain",
            "Team 2 Name": "Austria",
            "Team 1 Logo": "https://static-live.linewgen.xyz/live/bing/img/rapid/teams/9.png",
            "Team 2 Logo": "https://static-live.linewgen.xyz/live/bing/img/rapid/teams/775.png",
            "Match Title": "Spain VS Austria | World Cup",
            "Match Poster": "https://raw.githubusercontent.com/srhady/axsports/main/bing_posters/Spain_VS_Austria_World_Cup.jpg",
            "Match Status": "Upcoming",
            "Start Time": "1:00 AM 03-07-2026",
            "User-Agent": "Mozilla/5.0 (Linux; Android 10; K) AppleWebKit/537.36 (KHTML, like Gecko) Chrome/120.0.0.0 Mobile Safari/537.36",
            "Referer": "https://iframe.rumsport10.live/",
            "Stream URL": []
        },
        {
            "Category": "World Cup",
            "League": "World Cup",
            "Team 1 Name": "Portugal",
            "Team 2 Name": "Croatia",
            "Team 1 Logo": "https://static-live.linewgen.xyz/live/bing/img/rapid/teams/27.png",
            "Team 2 Logo": "https://static-live.linewgen.xyz/live/bing/img/rapid/teams/3.png",
            "Match Title": "Portugal VS Croatia | World Cup",
            "Match Poster": "https://raw.githubusercontent.com/srhady/axsports/main/bing_posters/Portugal_VS_Croatia_World_Cup.jpg",
            "Match Status": "Upcoming",
            "Start Time": "5:00 AM 03-07-2026",
            "User-Agent": "Mozilla/5.0 (Linux; Android 10; K) AppleWebKit/537.36 (KHTML, like Gecko) Chrome/120.0.0.0 Mobile Safari/537.36",
            "Referer": "https://iframe.rumsport10.live/",
            "Stream URL": []
        },
        {
            "Category": "World Cup",
            "League": "World Cup",
            "Team 1 Name": "Argentina",
            "Team 2 Name": "Cape Verde Islands",
            "Team 1 Logo": "https://static-live.linewgen.xyz/live/bing/img/rapid/teams/26.png",
            "Team 2 Logo": "https://static-live.linewgen.xyz/live/bing/img/rapid/teams/1533.png",
            "Match Title": "Argentina VS Cape Verde Islands | World Cup",
            "Match Poster": "https://raw.githubusercontent.com/srhady/axsports/main/bing_posters/Argentina_VS_Cape_Verde_Islands_World_Cup.jpg",
            "Match Status": "Upcoming",
            "Start Time": "4:00 AM 04-07-2026",
            "User-Agent": "Mozilla/5.0 (Linux; Android 10; K) AppleWebKit/537.36 (KHTML, like Gecko) Chrome/120.0.0.0 Mobile Safari/537.36",
            "Referer": "https://iframe.rumsport10.live/",
            "Stream URL": []
        }
    ]
}