{
    "playlist_info": {
        "name": "Bingstream Auto Update Playlist",
        "telegram": "https://t.me/livesportsplay",
        "owner": "Md Sohanur Rahman Hady",
        "last_update_time": "10:46:29 AM 16-04-2026"
    },
    "channels": [
        {
            "Category": "LIVE EVENT",
            "League": "Intro",
            "Team 1 Name": "Bingstream",
            "Team 2 Name": "Intro",
            "Team 1 Logo": "https://github.com/srhady/Hady/raw/refs/heads/main/1773124095740.png",
            "Team 2 Logo": "https://github.com/srhady/Hady/raw/refs/heads/main/1773124095740.png",
            "Match Title": "Intro",
            "Match Poster": "https://github.com/srhady/Hady/raw/refs/heads/main/1773124095740.png",
            "Match Status": "Live",
            "Start Time": "Always",
            "User-Agent": "Mozilla/5.0 (Linux; Android 10; K) AppleWebKit/537.36 (KHTML, like Gecko) Chrome/120.0.0.0 Mobile Safari/537.36",
            "Referer": "https://api2.ifnewgen.xyz/",
            "Stream URL": "https://github.com/srhady/Hady/raw/refs/heads/main/video_20260310_131739_edit.mp4"
        },
        {
            "Category": "NPB Farm Leagues",
            "League": "NPB Farm Leagues",
            "Team 1 Name": "",
            "Team 2 Name": "",
            "Team 1 Logo": "",
            "Team 2 Logo": "",
            "Match Title": "Chiba Lotte Marines VS Oisix Niigata | NPB Farm Leagues",
            "Match Poster": "https://placehold.co/800x450/ffffff/000000.png?text=Chiba%20Lotte%20Marines%0AVS%0AOisix%20Niigata%0ANPB%20Farm%20Leagues&font=Oswald",
            "Match Status": "Live",
            "Start Time": "Live Now",
            "User-Agent": "Mozilla/5.0 (Linux; Android 10; K) AppleWebKit/537.36 (KHTML, like Gecko) Chrome/120.0.0.0 Mobile Safari/537.36",
            "Referer": "https://api2.ifnewgen.xyz/",
            "Stream URL": ""
        },
        {
            "Category": "Football",
            "League": "CONCACAF Champions League",
            "Team 1 Name": "Seattle Sounders",
            "Team 2 Name": "Tigres UANL",
            "Team 1 Logo": "https://static-live.linewgen.xyz/live/bing/img/rapid/teams/1595.png",
            "Team 2 Logo": "https://static-live.linewgen.xyz/live/bing/img/rapid/teams/2279.png",
            "Match Title": "Seattle Sounders VS Tigres UANL | CONCACAF Champions League",
            "Match Poster": "https://placehold.co/800x450/ffffff/000000.png?text=Seattle%20Sounders%0AVS%0ATigres%20UANL%0ACONCACAF%20Champions%20League&font=Oswald",
            "Match Status": "Live",
            "Start Time": "Live Now",
            "User-Agent": "Mozilla/5.0 (Linux; Android 10; K) AppleWebKit/537.36 (KHTML, like Gecko) Chrome/120.0.0.0 Mobile Safari/537.36",
            "Referer": "https://api2.ifnewgen.xyz/",
            "Stream URL": "https://livecdn-bp-iptv.linewgen.xyz/live_abr/451_hd/index.m3u8?is_vip=false&token=f6cd7658616c7e8f7f0caf7c97ca9584948d6adf&x-sign=6a8251a38c90b83769676ea5f34deca4&x-time=1776314760"
        },
        {
            "Category": "Baseball",
            "League": "NPB Farm Leagues",
            "Team 1 Name": "Hanshin Tigers",
            "Team 2 Name": "Fukuoka SoftBank Hawks",
            "Team 1 Logo": "https://static-live.linewgen.xyz/live/bing/img/teams/5a915504baf84e88cbc763dfcfc934cf.png",
            "Team 2 Logo": "https://static-live.linewgen.xyz/live/bing/img/teams/711743b3437e10f4fe95736e0035a3b8.png",
            "Match Title": "Hanshin Tigers VS Fukuoka SoftBank Hawks | NPB Farm Leagues",
            "Match Poster": "https://placehold.co/800x450/ffffff/000000.png?text=Hanshin%20Tigers%0AVS%0AFukuoka%20SoftBank%20Hawks%0ANPB%20Farm%20Leagues&font=Oswald",
            "Match Status": "Live",
            "Start Time": "Live Now",
            "User-Agent": "Mozilla/5.0 (Linux; Android 10; K) AppleWebKit/537.36 (KHTML, like Gecko) Chrome/120.0.0.0 Mobile Safari/537.36",
            "Referer": "https://api2.ifnewgen.xyz/",
            "Stream URL": ""
        },
        {
            "Category": "UEFA Europa League",
            "League": "UEFA Europa League",
            "Team 1 Name": "Aston Villa",
            "Team 2 Name": "Bologna",
            "Team 1 Logo": "https://static-live.linewgen.xyz/live/bing/img/rapid/teams/66.png",
            "Team 2 Logo": "https://static-live.linewgen.xyz/live/bing/img/rapid/teams/500.png",
            "Match Title": "Aston Villa VS Bologna | UEFA Europa League",
            "Match Poster": "https://placehold.co/800x450/ffffff/000000.png?text=Aston%20Villa%0AVS%0ABologna%0AUEFA%20Europa%20League&font=Oswald",
            "Match Status": "Upcoming",
            "Start Time": "1:00 AM 17-04-2026",
            "User-Agent": "Mozilla/5.0 (Linux; Android 10; K) AppleWebKit/537.36 (KHTML, like Gecko) Chrome/120.0.0.0 Mobile Safari/537.36",
            "Referer": "https://api2.ifnewgen.xyz/",
            "Stream URL": ""
        },
        {
            "Category": "UEFA Europa League",
            "League": "UEFA Europa League",
            "Team 1 Name": "Nottingham Forest",
            "Team 2 Name": "FC Porto",
            "Team 1 Logo": "https://static-live.linewgen.xyz/live/bing/img/rapid/teams/65.png",
            "Team 2 Logo": "https://static-live.linewgen.xyz/live/bing/img/rapid/teams/212.png",
            "Match Title": "Nottingham Forest VS FC Porto | UEFA Europa League",
            "Match Poster": "https://placehold.co/800x450/ffffff/000000.png?text=Nottingham%20Forest%0AVS%0AFC%20Porto%0AUEFA%20Europa%20League&font=Oswald",
            "Match Status": "Upcoming",
            "Start Time": "1:00 AM 17-04-2026",
            "User-Agent": "Mozilla/5.0 (Linux; Android 10; K) AppleWebKit/537.36 (KHTML, like Gecko) Chrome/120.0.0.0 Mobile Safari/537.36",
            "Referer": "https://api2.ifnewgen.xyz/",
            "Stream URL": ""
        },
        {
            "Category": "UEFA Europa Conference League",
            "League": "UEFA Europa Conference League",
            "Team 1 Name": "Fiorentina",
            "Team 2 Name": "Crystal Palace",
            "Team 1 Logo": "https://static-live.linewgen.xyz/live/bing/img/rapid/teams/502.png",
            "Team 2 Logo": "https://static-live.linewgen.xyz/live/bing/img/rapid/teams/52.png",
            "Match Title": "Fiorentina VS Crystal Palace | UEFA Europa Conference League",
            "Match Poster": "https://placehold.co/800x450/ffffff/000000.png?text=Fiorentina%0AVS%0ACrystal%20Palace%0AUEFA%20Europa%20Conference%20League&font=Oswald",
            "Match Status": "Upcoming",
            "Start Time": "1:00 AM 17-04-2026",
            "User-Agent": "Mozilla/5.0 (Linux; Android 10; K) AppleWebKit/537.36 (KHTML, like Gecko) Chrome/120.0.0.0 Mobile Safari/537.36",
            "Referer": "https://api2.ifnewgen.xyz/",
            "Stream URL": ""
        },
        {
            "Category": "Serie A",
            "League": "Serie A",
            "Team 1 Name": "Inter",
            "Team 2 Name": "Cagliari",
            "Team 1 Logo": "https://static-live.linewgen.xyz/live/bing/img/teams/4fc97eac714aac61697dffd0e2cc714b.png",
            "Team 2 Logo": "https://static-live.linewgen.xyz/live/bing/img/rapid/teams/490.png",
            "Match Title": "Inter VS Cagliari | Serie A",
            "Match Poster": "https://placehold.co/800x450/ffffff/000000.png?text=Inter%0AVS%0ACagliari%0ASerie%20A&font=Oswald",
            "Match Status": "Upcoming",
            "Start Time": "12:45 AM 18-04-2026",
            "User-Agent": "Mozilla/5.0 (Linux; Android 10; K) AppleWebKit/537.36 (KHTML, like Gecko) Chrome/120.0.0.0 Mobile Safari/537.36",
            "Referer": "https://api2.ifnewgen.xyz/",
            "Stream URL": ""
        },
        {
            "Category": "Premier League",
            "League": "Premier League",
            "Team 1 Name": "Brentford",
            "Team 2 Name": "Fulham",
            "Team 1 Logo": "https://static-live.linewgen.xyz/live/bing/img/rapid/teams/55.png",
            "Team 2 Logo": "https://static-live.linewgen.xyz/live/bing/img/rapid/teams/36.png",
            "Match Title": "Brentford VS Fulham | Premier League",
            "Match Poster": "https://placehold.co/800x450/ffffff/000000.png?text=Brentford%0AVS%0AFulham%0APremier%20League&font=Oswald",
            "Match Status": "Upcoming",
            "Start Time": "5:30 PM 18-04-2026",
            "User-Agent": "Mozilla/5.0 (Linux; Android 10; K) AppleWebKit/537.36 (KHTML, like Gecko) Chrome/120.0.0.0 Mobile Safari/537.36",
            "Referer": "https://api2.ifnewgen.xyz/",
            "Stream URL": ""
        },
        {
            "Category": "Championship",
            "League": "Championship",
            "Team 1 Name": "Portsmouth",
            "Team 2 Name": "Leicester",
            "Team 1 Logo": "https://static-live.linewgen.xyz/live/bing/img/rapid/teams/1355.png",
            "Team 2 Logo": "https://static-live.linewgen.xyz/live/bing/img/rapid/teams/46.png",
            "Match Title": "Portsmouth VS Leicester | Championship",
            "Match Poster": "https://placehold.co/800x450/ffffff/000000.png?text=Portsmouth%0AVS%0ALeicester%0AChampionship&font=Oswald",
            "Match Status": "Upcoming",
            "Start Time": "5:30 PM 18-04-2026",
            "User-Agent": "Mozilla/5.0 (Linux; Android 10; K) AppleWebKit/537.36 (KHTML, like Gecko) Chrome/120.0.0.0 Mobile Safari/537.36",
            "Referer": "https://api2.ifnewgen.xyz/",
            "Stream URL": ""
        },
        {
            "Category": "Bundesliga",
            "League": "Bundesliga",
            "Team 1 Name": "1899 Hoffenheim",
            "Team 2 Name": "Borussia Dortmund",
            "Team 1 Logo": "https://static-live.linewgen.xyz/live/bing/img/rapid/teams/167.png",
            "Team 2 Logo": "https://static-live.linewgen.xyz/live/bing/img/rapid/teams/165.png",
            "Match Title": "1899 Hoffenheim VS Borussia Dortmund | Bundesliga",
            "Match Poster": "https://placehold.co/800x450/ffffff/000000.png?text=1899%20Hoffenheim%0AVS%0ABorussia%20Dortmund%0ABundesliga&font=Oswald",
            "Match Status": "Upcoming",
            "Start Time": "7:30 PM 18-04-2026",
            "User-Agent": "Mozilla/5.0 (Linux; Android 10; K) AppleWebKit/537.36 (KHTML, like Gecko) Chrome/120.0.0.0 Mobile Safari/537.36",
            "Referer": "https://api2.ifnewgen.xyz/",
            "Stream URL": ""
        },
        {
            "Category": "Football",
            "League": "AFL Premiership",
            "Team 1 Name": "Collingwood Magpies",
            "Team 2 Name": "Carlton Blues",
            "Team 1 Logo": "https://static-live.linewgen.xyz/live/bing/img/teams/18f6a18f318f475c05de8ae58353d3ca.png",
            "Team 2 Logo": "https://static-live.linewgen.xyz/live/bing/img/teams/dbeef5bf4aaa116207b6471898bf06b0.png",
            "Match Title": "Collingwood Magpies VS Carlton Blues | AFL Premiership",
            "Match Poster": "https://placehold.co/800x450/ffffff/000000.png?text=Collingwood%20Magpies%0AVS%0ACarlton%20Blues%0AAFL%20Premiership&font=Oswald",
            "Match Status": "Upcoming",
            "Start Time": "3:30 PM 16-04-2026",
            "User-Agent": "Mozilla/5.0 (Linux; Android 10; K) AppleWebKit/537.36 (KHTML, like Gecko) Chrome/120.0.0.0 Mobile Safari/537.36",
            "Referer": "https://api2.ifnewgen.xyz/",
            "Stream URL": ""
        },
        {
            "Category": "Football",
            "League": "Friendlies Women",
            "Team 1 Name": "Turks and Caicos Islands W",
            "Team 2 Name": "Mauritania W",
            "Team 1 Logo": "https://static-live.linewgen.xyz/live/bing/img/rapid/teams/19146.png",
            "Team 2 Logo": "https://static-live.linewgen.xyz/live/bing/img/rapid/teams/26918.png",
            "Match Title": "Turks and Caicos Islands W VS Mauritania W | Friendlies Women",
            "Match Poster": "https://placehold.co/800x450/ffffff/000000.png?text=Turks%20and%20Caicos%20Islands%20W%0AVS%0AMauritania%20W%0AFriendlies%20Women&font=Oswald",
            "Match Status": "Upcoming",
            "Start Time": "10:00 PM 16-04-2026",
            "User-Agent": "Mozilla/5.0 (Linux; Android 10; K) AppleWebKit/537.36 (KHTML, like Gecko) Chrome/120.0.0.0 Mobile Safari/537.36",
            "Referer": "https://api2.ifnewgen.xyz/",
            "Stream URL": ""
        },
        {
            "Category": "Football",
            "League": "UEFA Europa Conference League",
            "Team 1 Name": "AZ Alkmaar",
            "Team 2 Name": "Shakhtar Donetsk",
            "Team 1 Logo": "https://static-live.linewgen.xyz/live/bing/img/rapid/teams/201.png",
            "Team 2 Logo": "https://static-live.linewgen.xyz/live/bing/img/rapid/teams/550.png",
            "Match Title": "AZ Alkmaar VS Shakhtar Donetsk | UEFA Europa Conference League",
            "Match Poster": "https://placehold.co/800x450/ffffff/000000.png?text=AZ%20Alkmaar%0AVS%0AShakhtar%20Donetsk%0AUEFA%20Europa%20Conference%20League&font=Oswald",
            "Match Status": "Upcoming",
            "Start Time": "10:45 PM 16-04-2026",
            "User-Agent": "Mozilla/5.0 (Linux; Android 10; K) AppleWebKit/537.36 (KHTML, like Gecko) Chrome/120.0.0.0 Mobile Safari/537.36",
            "Referer": "https://api2.ifnewgen.xyz/",
            "Stream URL": ""
        },
        {
            "Category": "Football",
            "League": "UEFA Europa League",
            "Team 1 Name": "Celta Vigo",
            "Team 2 Name": "SC Freiburg",
            "Team 1 Logo": "https://static-live.linewgen.xyz/live/bing/img/rapid/teams/538.png",
            "Team 2 Logo": "https://static-live.linewgen.xyz/live/bing/img/rapid/teams/160.png",
            "Match Title": "Celta Vigo VS SC Freiburg | UEFA Europa League",
            "Match Poster": "https://placehold.co/800x450/ffffff/000000.png?text=Celta%20Vigo%0AVS%0ASC%20Freiburg%0AUEFA%20Europa%20League&font=Oswald",
            "Match Status": "Upcoming",
            "Start Time": "10:45 PM 16-04-2026",
            "User-Agent": "Mozilla/5.0 (Linux; Android 10; K) AppleWebKit/537.36 (KHTML, like Gecko) Chrome/120.0.0.0 Mobile Safari/537.36",
            "Referer": "https://api2.ifnewgen.xyz/",
            "Stream URL": ""
        },
        {
            "Category": "Football",
            "League": "League One",
            "Team 1 Name": "Peterborough",
            "Team 2 Name": "Port Vale",
            "Team 1 Logo": "https://static-live.linewgen.xyz/live/bing/img/rapid/teams/1350.png",
            "Team 2 Logo": "https://static-live.linewgen.xyz/live/bing/img/rapid/teams/1351.png",
            "Match Title": "Peterborough VS Port Vale | League One",
            "Match Poster": "https://placehold.co/800x450/ffffff/000000.png?text=Peterborough%0AVS%0APort%20Vale%0ALeague%20One&font=Oswald",
            "Match Status": "Upcoming",
            "Start Time": "12:45 AM 17-04-2026",
            "User-Agent": "Mozilla/5.0 (Linux; Android 10; K) AppleWebKit/537.36 (KHTML, like Gecko) Chrome/120.0.0.0 Mobile Safari/537.36",
            "Referer": "https://api2.ifnewgen.xyz/",
            "Stream URL": ""
        },
        {
            "Category": "Football",
            "League": "League Two",
            "Team 1 Name": "Bromley",
            "Team 2 Name": "Cambridge United",
            "Team 1 Logo": "https://static-live.linewgen.xyz/live/bing/img/rapid/teams/1832.png",
            "Team 2 Logo": "https://static-live.linewgen.xyz/live/bing/img/rapid/teams/1370.png",
            "Match Title": "Bromley VS Cambridge United | League Two",
            "Match Poster": "https://placehold.co/800x450/ffffff/000000.png?text=Bromley%0AVS%0ACambridge%20United%0ALeague%20Two&font=Oswald",
            "Match Status": "Upcoming",
            "Start Time": "1:00 AM 17-04-2026",
            "User-Agent": "Mozilla/5.0 (Linux; Android 10; K) AppleWebKit/537.36 (KHTML, like Gecko) Chrome/120.0.0.0 Mobile Safari/537.36",
            "Referer": "https://api2.ifnewgen.xyz/",
            "Stream URL": ""
        },
        {
            "Category": "Football",
            "League": "UEFA Europa Conference League",
            "Team 1 Name": "Strasbourg",
            "Team 2 Name": "FSV Mainz 05",
            "Team 1 Logo": "https://static-live.linewgen.xyz/live/bing/img/rapid/teams/95.png",
            "Team 2 Logo": "https://static-live.linewgen.xyz/live/bing/img/rapid/teams/164.png",
            "Match Title": "Strasbourg VS FSV Mainz 05 | UEFA Europa Conference League",
            "Match Poster": "https://placehold.co/800x450/ffffff/000000.png?text=Strasbourg%0AVS%0AFSV%20Mainz%2005%0AUEFA%20Europa%20Conference%20League&font=Oswald",
            "Match Status": "Upcoming",
            "Start Time": "1:00 AM 17-04-2026",
            "User-Agent": "Mozilla/5.0 (Linux; Android 10; K) AppleWebKit/537.36 (KHTML, like Gecko) Chrome/120.0.0.0 Mobile Safari/537.36",
            "Referer": "https://api2.ifnewgen.xyz/",
            "Stream URL": ""
        },
        {
            "Category": "Football",
            "League": "UEFA Europa Conference League",
            "Team 1 Name": "AEK Athens FC",
            "Team 2 Name": "Rayo Vallecano",
            "Team 1 Logo": "https://static-live.linewgen.xyz/live/bing/img/rapid/teams/575.png",
            "Team 2 Logo": "https://static-live.linewgen.xyz/live/bing/img/rapid/teams/728.png",
            "Match Title": "AEK Athens FC VS Rayo Vallecano | UEFA Europa Conference League",
            "Match Poster": "https://placehold.co/800x450/ffffff/000000.png?text=AEK%20Athens%20FC%0AVS%0ARayo%20Vallecano%0AUEFA%20Europa%20Conference%20League&font=Oswald",
            "Match Status": "Upcoming",
            "Start Time": "1:00 AM 17-04-2026",
            "User-Agent": "Mozilla/5.0 (Linux; Android 10; K) AppleWebKit/537.36 (KHTML, like Gecko) Chrome/120.0.0.0 Mobile Safari/537.36",
            "Referer": "https://api2.ifnewgen.xyz/",
            "Stream URL": ""
        },
        {
            "Category": "Football",
            "League": "UEFA Europa League",
            "Team 1 Name": "Real Betis",
            "Team 2 Name": "SC Braga",
            "Team 1 Logo": "https://static-live.linewgen.xyz/live/bing/img/rapid/teams/543.png",
            "Team 2 Logo": "https://static-live.linewgen.xyz/live/bing/img/rapid/teams/217.png",
            "Match Title": "Real Betis VS SC Braga | UEFA Europa League",
            "Match Poster": "https://placehold.co/800x450/ffffff/000000.png?text=Real%20Betis%0AVS%0ASC%20Braga%0AUEFA%20Europa%20League&font=Oswald",
            "Match Status": "Upcoming",
            "Start Time": "1:00 AM 17-04-2026",
            "User-Agent": "Mozilla/5.0 (Linux; Android 10; K) AppleWebKit/537.36 (KHTML, like Gecko) Chrome/120.0.0.0 Mobile Safari/537.36",
            "Referer": "https://api2.ifnewgen.xyz/",
            "Stream URL": ""
        },
        {
            "Category": "Football",
            "League": "Friendlies Women",
            "Team 1 Name": "Ivory Coast W",
            "Team 2 Name": "Pakistan W",
            "Team 1 Logo": "https://static-live.linewgen.xyz/live/bing/img/rapid/teams/1734.png",
            "Team 2 Logo": "https://static-live.linewgen.xyz/live/bing/img/rapid/teams/20806.png",
            "Match Title": "Ivory Coast W VS Pakistan W | Friendlies Women",
            "Match Poster": "https://placehold.co/800x450/ffffff/000000.png?text=Ivory%20Coast%20W%0AVS%0APakistan%20W%0AFriendlies%20Women&font=Oswald",
            "Match Status": "Upcoming",
            "Start Time": "1:30 AM 17-04-2026",
            "User-Agent": "Mozilla/5.0 (Linux; Android 10; K) AppleWebKit/537.36 (KHTML, like Gecko) Chrome/120.0.0.0 Mobile Safari/537.36",
            "Referer": "https://api2.ifnewgen.xyz/",
            "Stream URL": ""
        },
        {
            "Category": "Football",
            "League": "CONMEBOL Sudamericana",
            "Team 1 Name": "Tigre",
            "Team 2 Name": "Macara",
            "Team 1 Logo": "https://static-live.linewgen.xyz/live/bing/img/rapid/teams/452.png",
            "Team 2 Logo": "https://static-live.linewgen.xyz/live/bing/img/rapid/teams/1155.png",
            "Match Title": "Tigre VS Macara | CONMEBOL Sudamericana",
            "Match Poster": "https://placehold.co/800x450/ffffff/000000.png?text=Tigre%0AVS%0AMacara%0ACONMEBOL%20Sudamericana&font=Oswald",
            "Match Status": "Upcoming",
            "Start Time": "4:00 AM 17-04-2026",
            "User-Agent": "Mozilla/5.0 (Linux; Android 10; K) AppleWebKit/537.36 (KHTML, like Gecko) Chrome/120.0.0.0 Mobile Safari/537.36",
            "Referer": "https://api2.ifnewgen.xyz/",
            "Stream URL": ""
        },
        {
            "Category": "Football",
            "League": "CONMEBOL Libertadores",
            "Team 1 Name": "Palmeiras",
            "Team 2 Name": "Sporting Cristal",
            "Team 1 Logo": "https://static-live.linewgen.xyz/live/bing/img/rapid/teams/121.png",
            "Team 2 Logo": "https://static-live.linewgen.xyz/live/bing/img/rapid/teams/2546.png",
            "Match Title": "Palmeiras VS Sporting Cristal | CONMEBOL Libertadores",
            "Match Poster": "https://placehold.co/800x450/ffffff/000000.png?text=Palmeiras%0AVS%0ASporting%20Cristal%0ACONMEBOL%20Libertadores&font=Oswald",
            "Match Status": "Upcoming",
            "Start Time": "4:00 AM 17-04-2026",
            "User-Agent": "Mozilla/5.0 (Linux; Android 10; K) AppleWebKit/537.36 (KHTML, like Gecko) Chrome/120.0.0.0 Mobile Safari/537.36",
            "Referer": "https://api2.ifnewgen.xyz/",
            "Stream URL": ""
        },
        {
            "Category": "Football",
            "League": "CONMEBOL Sudamericana",
            "Team 1 Name": "RB Bragantino",
            "Team 2 Name": "Blooming",
            "Team 1 Logo": "https://static-live.linewgen.xyz/live/bing/img/rapid/teams/794.png",
            "Team 2 Logo": "https://static-live.linewgen.xyz/live/bing/img/rapid/teams/3701.png",
            "Match Title": "RB Bragantino VS Blooming | CONMEBOL Sudamericana",
            "Match Poster": "https://placehold.co/800x450/ffffff/000000.png?text=RB%20Bragantino%0AVS%0ABlooming%0ACONMEBOL%20Sudamericana&font=Oswald",
            "Match Status": "Upcoming",
            "Start Time": "6:30 AM 17-04-2026",
            "User-Agent": "Mozilla/5.0 (Linux; Android 10; K) AppleWebKit/537.36 (KHTML, like Gecko) Chrome/120.0.0.0 Mobile Safari/537.36",
            "Referer": "https://api2.ifnewgen.xyz/",
            "Stream URL": ""
        },
        {
            "Category": "Football",
            "League": "CONMEBOL Libertadores",
            "Team 1 Name": "Flamengo",
            "Team 2 Name": "Independiente Medellin",
            "Team 1 Logo": "https://static-live.linewgen.xyz/live/bing/img/rapid/teams/127.png",
            "Team 2 Logo": "https://static-live.linewgen.xyz/live/bing/img/rapid/teams/1128.png",
            "Match Title": "Flamengo VS Independiente Medellin | CONMEBOL Libertadores",
            "Match Poster": "https://placehold.co/800x450/ffffff/000000.png?text=Flamengo%0AVS%0AIndependiente%20Medellin%0ACONMEBOL%20Libertadores&font=Oswald",
            "Match Status": "Upcoming",
            "Start Time": "6:30 AM 17-04-2026",
            "User-Agent": "Mozilla/5.0 (Linux; Android 10; K) AppleWebKit/537.36 (KHTML, like Gecko) Chrome/120.0.0.0 Mobile Safari/537.36",
            "Referer": "https://api2.ifnewgen.xyz/",
            "Stream URL": ""
        },
        {
            "Category": "Football",
            "League": "CONMEBOL Sudamericana",
            "Team 1 Name": "Cienciano",
            "Team 2 Name": "Puerto Cabello",
            "Team 1 Logo": "https://static-live.linewgen.xyz/live/bing/img/rapid/teams/2562.png",
            "Team 2 Logo": "https://static-live.linewgen.xyz/live/bing/img/rapid/teams/2827.png",
            "Match Title": "Cienciano VS Puerto Cabello | CONMEBOL Sudamericana",
            "Match Poster": "https://placehold.co/800x450/ffffff/000000.png?text=Cienciano%0AVS%0APuerto%20Cabello%0ACONMEBOL%20Sudamericana&font=Oswald",
            "Match Status": "Upcoming",
            "Start Time": "8:00 AM 17-04-2026",
            "User-Agent": "Mozilla/5.0 (Linux; Android 10; K) AppleWebKit/537.36 (KHTML, like Gecko) Chrome/120.0.0.0 Mobile Safari/537.36",
            "Referer": "https://api2.ifnewgen.xyz/",
            "Stream URL": ""
        },
        {
            "Category": "Tennis",
            "League": "Stuttgart Open",
            "Team 1 Name": "",
            "Team 2 Name": "",
            "Team 1 Logo": "",
            "Team 2 Logo": "",
            "Match Title": "Day 4 | Stuttgart Open",
            "Match Poster": "https://placehold.co/800x450/ffffff/000000.png?text=Day%204%0AStuttgart%20Open&font=Oswald",
            "Match Status": "Upcoming",
            "Start Time": "4:30 PM 16-04-2026",
            "User-Agent": "Mozilla/5.0 (Linux; Android 10; K) AppleWebKit/537.36 (KHTML, like Gecko) Chrome/120.0.0.0 Mobile Safari/537.36",
            "Referer": "https://api2.ifnewgen.xyz/",
            "Stream URL": ""
        },
        {
            "Category": "Basketball",
            "League": "Euroleague",
            "Team 1 Name": "LDLC ASVEL Villeurbanne",
            "Team 2 Name": "Fenerbahce Beko Istanbul",
            "Team 1 Logo": "https://static-live.linewgen.xyz/live/bing/img/teams/d07c0541744292743eacf75466bf9385.png",
            "Team 2 Logo": "https://static-live.linewgen.xyz/live/bing/img/teams/44e853b64dc979f2f66fb04f08ef0d74.png",
            "Match Title": "LDLC ASVEL Villeurbanne VS Fenerbahce Beko Istanbul | Euroleague",
            "Match Poster": "https://placehold.co/800x450/ffffff/000000.png?text=LDLC%20ASVEL%20Villeurbanne%0AVS%0AFenerbahce%20Beko%20Istanbul%0AEuroleague&font=Oswald",
            "Match Status": "Upcoming",
            "Start Time": "12:00 AM 17-04-2026",
            "User-Agent": "Mozilla/5.0 (Linux; Android 10; K) AppleWebKit/537.36 (KHTML, like Gecko) Chrome/120.0.0.0 Mobile Safari/537.36",
            "Referer": "https://api2.ifnewgen.xyz/",
            "Stream URL": ""
        },
        {
            "Category": "Basketball",
            "League": "Euroleague",
            "Team 1 Name": "Maccabi Rapyd Tel Aviv",
            "Team 2 Name": "Virtus Bologna",
            "Team 1 Logo": "https://static-live.linewgen.xyz/live/bing/img/teams/8517d981a8b9f3b3a253b8cdbe48a3fc.png",
            "Team 2 Logo": "https://static-live.linewgen.xyz/live/bing/img/teams/abea4d08a7bea44a68ef63b37257fea3.png",
            "Match Title": "Maccabi Rapyd Tel Aviv VS Virtus Bologna | Euroleague",
            "Match Poster": "https://placehold.co/800x450/ffffff/000000.png?text=Maccabi%20Rapyd%20Tel%20Aviv%0AVS%0AVirtus%20Bologna%0AEuroleague&font=Oswald",
            "Match Status": "Upcoming",
            "Start Time": "12:00 AM 17-04-2026",
            "User-Agent": "Mozilla/5.0 (Linux; Android 10; K) AppleWebKit/537.36 (KHTML, like Gecko) Chrome/120.0.0.0 Mobile Safari/537.36",
            "Referer": "https://api2.ifnewgen.xyz/",
            "Stream URL": ""
        },
        {
            "Category": "Basketball",
            "League": "Euroleague",
            "Team 1 Name": "Olympiacos Piraeus Basketball",
            "Team 2 Name": "EA7 Emporio Armani Milan",
            "Team 1 Logo": "https://static-live.linewgen.xyz/live/bing/img/teams/bc561d524df62d76538d46a80b95ccc7.png",
            "Team 2 Logo": "https://static-live.linewgen.xyz/live/bing/img/teams/93b216bb4128cd7393a39fe27b39c1af.png",
            "Match Title": "Olympiacos Piraeus Basketball VS EA7 Emporio Armani Milan | Euroleague",
            "Match Poster": "https://placehold.co/800x450/ffffff/000000.png?text=Olympiacos%20Piraeus%20Basketball%0AVS%0AEA7%20Emporio%20Armani%20Milan%0AEuroleague&font=Oswald",
            "Match Status": "Upcoming",
            "Start Time": "12:15 AM 17-04-2026",
            "User-Agent": "Mozilla/5.0 (Linux; Android 10; K) AppleWebKit/537.36 (KHTML, like Gecko) Chrome/120.0.0.0 Mobile Safari/537.36",
            "Referer": "https://api2.ifnewgen.xyz/",
            "Stream URL": ""
        },
        {
            "Category": "Baseball",
            "League": "NPB Farm Leagues",
            "Team 1 Name": "",
            "Team 2 Name": "",
            "Team 1 Logo": "",
            "Team 2 Logo": "",
            "Match Title": "Hayate Shizuoka VS Yomiuri Giants | NPB Farm Leagues",
            "Match Poster": "https://placehold.co/800x450/ffffff/000000.png?text=Hayate%20Shizuoka%0AVS%0AYomiuri%20Giants%0ANPB%20Farm%20Leagues&font=Oswald",
            "Match Status": "Upcoming",
            "Start Time": "11:00 AM 16-04-2026",
            "User-Agent": "Mozilla/5.0 (Linux; Android 10; K) AppleWebKit/537.36 (KHTML, like Gecko) Chrome/120.0.0.0 Mobile Safari/537.36",
            "Referer": "https://api2.ifnewgen.xyz/",
            "Stream URL": ""
        },
        {
            "Category": "Baseball",
            "League": "NPB",
            "Team 1 Name": "Chiba Lotte Marines",
            "Team 2 Name": "Hokkaido Nippon-Ham Fighters",
            "Team 1 Logo": "https://static-live.linewgen.xyz/live/bing/img/teams/f21f7f743a49b135f1804b1df2d0e5d8.png",
            "Team 2 Logo": "https://static-live.linewgen.xyz/live/bing/img/teams/329405cfcfea53d121091a4bee27b860.png",
            "Match Title": "Chiba Lotte Marines VS Hokkaido Nippon-Ham Fighters | NPB",
            "Match Poster": "https://placehold.co/800x450/ffffff/000000.png?text=Chiba%20Lotte%20Marines%0AVS%0AHokkaido%20Nippon-Ham%20Fighters%0ANPB&font=Oswald",
            "Match Status": "Upcoming",
            "Start Time": "3:00 PM 16-04-2026",
            "User-Agent": "Mozilla/5.0 (Linux; Android 10; K) AppleWebKit/537.36 (KHTML, like Gecko) Chrome/120.0.0.0 Mobile Safari/537.36",
            "Referer": "https://api2.ifnewgen.xyz/",
            "Stream URL": ""
        },
        {
            "Category": "Baseball",
            "League": "NPB",
            "Team 1 Name": "ORIX Buffaloes",
            "Team 2 Name": "Saitama Seibu Lions",
            "Team 1 Logo": "https://static-live.linewgen.xyz/live/bing/img/teams/152af9ee913c91f59154eaf2ae51db2f.png",
            "Team 2 Logo": "https://static-live.linewgen.xyz/live/bing/img/teams/f07b37d09423b49b22242408888547f6.png",
            "Match Title": "ORIX Buffaloes VS Saitama Seibu Lions | NPB",
            "Match Poster": "https://placehold.co/800x450/ffffff/000000.png?text=ORIX%20Buffaloes%0AVS%0ASaitama%20Seibu%20Lions%0ANPB&font=Oswald",
            "Match Status": "Upcoming",
            "Start Time": "3:00 PM 16-04-2026",
            "User-Agent": "Mozilla/5.0 (Linux; Android 10; K) AppleWebKit/537.36 (KHTML, like Gecko) Chrome/120.0.0.0 Mobile Safari/537.36",
            "Referer": "https://api2.ifnewgen.xyz/",
            "Stream URL": ""
        },
        {
            "Category": "Golf",
            "League": "LIV Golf",
            "Team 1 Name": "",
            "Team 2 Name": "",
            "Team 1 Logo": "",
            "Team 2 Logo": "",
            "Match Title": "LIV Golf Mexico City | LIV Golf",
            "Match Poster": "https://placehold.co/800x450/ffffff/000000.png?text=LIV%20Golf%20Mexico%20City%0ALIV%20Golf&font=Oswald",
            "Match Status": "Upcoming",
            "Start Time": "1:00 AM 17-04-2026",
            "User-Agent": "Mozilla/5.0 (Linux; Android 10; K) AppleWebKit/537.36 (KHTML, like Gecko) Chrome/120.0.0.0 Mobile Safari/537.36",
            "Referer": "https://api2.ifnewgen.xyz/",
            "Stream URL": ""
        },
        {
            "Category": "Rugby",
            "League": "World Rugby Sevens Series",
            "Team 1 Name": "",
            "Team 2 Name": "",
            "Team 1 Logo": "",
            "Team 2 Logo": "",
            "Match Title": "World Rugby Sevens Series | World Rugby Sevens Series",
            "Match Poster": "https://placehold.co/800x450/ffffff/000000.png?text=World%20Rugby%20Sevens%20Series%0AWorld%20Rugby%20Sevens%20Series&font=Oswald",
            "Match Status": "Upcoming",
            "Start Time": "8:30 AM 17-04-2026",
            "User-Agent": "Mozilla/5.0 (Linux; Android 10; K) AppleWebKit/537.36 (KHTML, like Gecko) Chrome/120.0.0.0 Mobile Safari/537.36",
            "Referer": "https://api2.ifnewgen.xyz/",
            "Stream URL": ""
        },
        {
            "Category": "Rugby",
            "League": "Super Rugby Pacific",
            "Team 1 Name": "Blues",
            "Team 2 Name": "Highlanders",
            "Team 1 Logo": "https://static-live.linewgen.xyz/live/bing/img/teams/8c5c86da27bcbd85aac60f697a12282a.png",
            "Team 2 Logo": "https://static-live.linewgen.xyz/live/bing/img/teams/06e0cb70c1e04a66d5a4f804122f6ba0.png",
            "Match Title": "Blues VS Highlanders | Super Rugby Pacific",
            "Match Poster": "https://placehold.co/800x450/ffffff/000000.png?text=Blues%0AVS%0AHighlanders%0ASuper%20Rugby%20Pacific&font=Oswald",
            "Match Status": "Upcoming",
            "Start Time": "12:30 PM 17-04-2026",
            "User-Agent": "Mozilla/5.0 (Linux; Android 10; K) AppleWebKit/537.36 (KHTML, like Gecko) Chrome/120.0.0.0 Mobile Safari/537.36",
            "Referer": "https://api2.ifnewgen.xyz/",
            "Stream URL": ""
        },
        {
            "Category": "Rugby",
            "League": "Super Rugby Pacific",
            "Team 1 Name": "Waratahs",
            "Team 2 Name": "Moana Pasifika",
            "Team 1 Logo": "https://static-live.linewgen.xyz/live/bing/img/teams/386cc98af10c58c60774777107d31d6a.png",
            "Team 2 Logo": "https://static-live.linewgen.xyz/live/bing/img/teams/ed95129328caafb2adc28d7bfd67ad6f.jpg",
            "Match Title": "Waratahs VS Moana Pasifika | Super Rugby Pacific",
            "Match Poster": "https://placehold.co/800x450/ffffff/000000.png?text=Waratahs%0AVS%0AMoana%20Pasifika%0ASuper%20Rugby%20Pacific&font=Oswald",
            "Match Status": "Upcoming",
            "Start Time": "3:00 PM 17-04-2026",
            "User-Agent": "Mozilla/5.0 (Linux; Android 10; K) AppleWebKit/537.36 (KHTML, like Gecko) Chrome/120.0.0.0 Mobile Safari/537.36",
            "Referer": "https://api2.ifnewgen.xyz/",
            "Stream URL": ""
        },
        {
            "Category": "Darts",
            "League": "Premier League",
            "Team 1 Name": "",
            "Team 2 Name": "",
            "Team 1 Logo": "",
            "Team 2 Logo": "",
            "Match Title": "Night 11 | Premier League",
            "Match Poster": "https://placehold.co/800x450/ffffff/000000.png?text=Night%2011%0APremier%20League&font=Oswald",
            "Match Status": "Upcoming",
            "Start Time": "11:00 PM 16-04-2026",
            "User-Agent": "Mozilla/5.0 (Linux; Android 10; K) AppleWebKit/537.36 (KHTML, like Gecko) Chrome/120.0.0.0 Mobile Safari/537.36",
            "Referer": "https://api2.ifnewgen.xyz/",
            "Stream URL": ""
        }
    ]
}